{"534421568261459968": {"raw_source": {"contributors": null, "truncated": false, "text": "8:00 p.m. against the #Hoos. Playing under the lights on TV, let discussions of the #BlackFridayBlackout begin. #Hokies cc: @WhitBabcock", "in_reply_to_status_id": null, "id": 534421568261459968, "favorite_count": 0, "source": "<a href=\"http://twitter.com\" rel=\"nofollow\">Twitter Web Client</a>", "retweeted": false, "coordinates": {"type": "Point", "coordinates": [0.0, 0.0]}, "entities": {"symbols": [], "user_mentions": [{"id": 241295538, "indices": [124, 136], "id_str": "241295538", "screen_name": "WhitBabcock", "name": "Whit Babcock        "}], "hashtags": [{"indices": [22, 27], "text": "Hoos"}, {"indices": [84, 104], "text": "BlackFridayBlackout"}, {"indices": [112, 119], "text": "Hokies"}], "urls": []}, "in_reply_to_screen_name": null, "in_reply_to_user_id": null, "retweet_count": 0, "id_str": "534421568261459968", "favorited": false, "user": {"follow_request_sent": null, "profile_use_background_image": true, "profile_text_color": "333333", "default_profile_image": false, "id": 90774385, "profile_background_image_url_https": "https://abs.twimg.com/images/themes/theme6/bg.gif", "verified": false, "profile_location": null, "profile_image_url_https": "https://pbs.twimg.com/profile_images/378800000537999720/7132c67dfa9852d82954ddbe7f336c85_normal.png", "profile_sidebar_fill_color": "A0C5C7", "entities": {"description": {"urls": []}}, "followers_count": 273, "profile_sidebar_border_color": "86A4A6", "id_str": "90774385", "profile_background_color": "709397", "listed_count": 7, "is_translation_enabled": false, "utc_offset": -21600, "statuses_count": 2798, "description": "Interests: Business, Capitalism, New Economy, Innovation, Strategy. Passions: @mshokie, Hokies, Capitals, Redskins.", "friends_count": 486, "location": "New York, NY", "profile_link_color": "FF3300", "profile_image_url": "http://pbs.twimg.com/profile_images/378800000537999720/7132c67dfa9852d82954ddbe7f336c85_normal.png", "following": null, "geo_enabled": true, "profile_banner_url": "https://pbs.twimg.com/profile_banners/90774385/1383223556", "profile_background_image_url": "http://abs.twimg.com/images/themes/theme6/bg.gif", "name": "Kerby", "lang": "en", "profile_background_tile": false, "favourites_count": 732, "screen_name": "KerbyHouff", "notifications": null, "url": null, "created_at": "Wed Nov 18 01:50:55 +0000 2009", "contributors_enabled": false, "time_zone": "Central Time (US & Canada)", "protected": false, "default_profile": false, "is_translator": false}, "geo": {"type": "Point", "coordinates": [0.0, 0.0]}, "in_reply_to_user_id_str": null, "lang": "en", "created_at": "Mon Nov 17 19:03:25 +0000 2014", "in_reply_to_status_id_str": null, "place": {"country_code": "US", "url": "https://api.twitter.com/1.1/geo/id/01a9a39529b27f36.json", "country": "United States", "place_type": "city", "bounding_box": {"type": "Polygon", "coordinates": [[[-74.026675, 40.683935], [-73.910408, 40.683935], [-73.910408, 40.877483], [-74.026675, 40.877483]]]}, "contained_within": [], "full_name": "Manhattan, NY", "attributes": {}, "id": "01a9a39529b27f36", "name": "Manhattan"}, "metadata": {"iso_language_code": "en", "result_type": "recent"}}, "data_point": "none", "user_location": "New York, NY", "lon": 0.0, "content": "8:00 p.m. against the #Hoos. Playing under the lights on TV, let discussions of the #BlackFridayBlackout begin. #Hokies cc: @WhitBabcock", "tweet_id": 534421568261459968, "user": 90774385, "time": "Mon Nov 17 19:03:25 +0000 2014", "lat": 0.0}, "534421572560236544": {"raw_source": {"contributors": null, "truncated": false, "text": "@ngarte Would you be interested in outsourcing your project?", "in_reply_to_status_id": 534176380226138112, "id": 534421572560236544, "favorite_count": 0, "source": "<a href=\"http://twitter.com\" rel=\"nofollow\">Twitter Web Client</a>", "retweeted": false, "coordinates": {"type": "Point", "coordinates": [0.0, 0.0]}, "entities": {"symbols": [], "user_mentions": [{"id": 38179148, "indices": [0, 7], "id_str": "38179148", "screen_name": "ngarte", "name": "Adrian Ng"}], "hashtags": [], "urls": []}, "in_reply_to_screen_name": "ngarte", "in_reply_to_user_id": 38179148, "retweet_count": 0, "id_str": "534421572560236544", "favorited": false, "user": {"follow_request_sent": null, "profile_use_background_image": true, "profile_text_color": "333333", "default_profile_image": false, "id": 278011163, "profile_background_image_url_https": "https://pbs.twimg.com/profile_background_images/852037659/f704cc4764beaf45fd255beda3fc77b5.jpeg", "verified": false, "profile_location": null, "profile_image_url_https": "https://pbs.twimg.com/profile_images/1301932832/Openwave_normal.jpg", "profile_sidebar_fill_color": "DDEEF6", "entities": {"url": {"urls": [{"url": "http://t.co/hJz5PkKEvo", "indices": [0, 22], "expanded_url": "http://about.me/App_Developers_New_York", "display_url": "about.me/App_Developers\u2026"}]}, "description": {"urls": []}}, "followers_count": 648, "profile_sidebar_border_color": "FFFFFF", "id_str": "278011163", "profile_background_color": "C0DEED", "listed_count": 9, "is_translation_enabled": false, "utc_offset": -18000, "statuses_count": 3476, "description": "Openwave Computing LLC, NYC an ISO 9001: 2008 certified mobile app Development Company who are on demand now!! We make all sorts of apps for varied platforms!", "friends_count": 1586, "location": "New York", "profile_link_color": "0084B4", "profile_image_url": "http://pbs.twimg.com/profile_images/1301932832/Openwave_normal.jpg", "following": null, "geo_enabled": true, "profile_banner_url": "https://pbs.twimg.com/profile_banners/278011163/1398260309", "profile_background_image_url": "http://pbs.twimg.com/profile_background_images/852037659/f704cc4764beaf45fd255beda3fc77b5.jpeg", "name": "Apps Development NYC", "lang": "en", "profile_background_tile": false, "favourites_count": 171, "screen_name": "OWCServices", "notifications": null, "url": "http://t.co/hJz5PkKEvo", "created_at": "Wed Apr 06 12:38:17 +0000 2011", "contributors_enabled": false, "time_zone": "Eastern Time (US & Canada)", "protected": false, "default_profile": false, "is_translator": false}, "geo": {"type": "Point", "coordinates": [0.0, 0.0]}, "in_reply_to_user_id_str": "38179148", "lang": "en", "created_at": "Mon Nov 17 19:03:26 +0000 2014", "in_reply_to_status_id_str": "534176380226138112", "place": {"country_code": "US", "url": "https://api.twitter.com/1.1/geo/id/94965b2c45386f87.json", "country": "United States", "place_type": "admin", "bounding_box": {"type": "Polygon", "coordinates": [[[-79.76259, 40.477383], [-71.777492, 40.477383], [-71.777492, 45.015851], [-79.76259, 45.015851]]]}, "contained_within": [], "full_name": "New York, US", "attributes": {}, "id": "94965b2c45386f87", "name": "New York"}, "metadata": {"iso_language_code": "en", "result_type": "recent"}}, "data_point": "none", "user_location": "New York", "lon": 0.0, "content": "@ngarte Would you be interested in outsourcing your project?", "tweet_id": 534421572560236544, "user": 278011163, "time": "Mon Nov 17 19:03:26 +0000 2014", "lat": 0.0}, "534421044967522304": {"raw_source": {"contributors": null, "truncated": false, "text": "10 Craziest Things We Learned From the Aaliyah Lifetime Movie http://t.co/NgzGVq6ZFT via @rollingstone", "in_reply_to_status_id": null, "id": 534421044967522304, "favorite_count": 0, "source": "<a href=\"http://twitter.com/download/iphone\" rel=\"nofollow\">Twitter for iPhone</a>", "retweeted": false, "coordinates": {"type": "Point", "coordinates": [-74.0262015, 40.74639438]}, "entities": {"symbols": [], "user_mentions": [{"id": 14780915, "indices": [89, 102], "id_str": "14780915", "screen_name": "RollingStone", "name": "Rolling Stone"}], "hashtags": [], "urls": [{"url": "http://t.co/NgzGVq6ZFT", "indices": [62, 84], "expanded_url": "http://rol.st/11k9iev", "display_url": "rol.st/11k9iev"}]}, "in_reply_to_screen_name": null, "in_reply_to_user_id": null, "retweet_count": 0, "id_str": "534421044967522304", "favorited": false, "user": {"follow_request_sent": null, "profile_use_background_image": true, "profile_text_color": "333333", "default_profile_image": false, "id": 2812367157, "profile_background_image_url_https": "https://abs.twimg.com/images/themes/theme1/bg.png", "verified": false, "profile_location": null, "profile_image_url_https": "https://pbs.twimg.com/profile_images/519316499366825984/pL2NtKzZ_normal.jpeg", "profile_sidebar_fill_color": "DDEEF6", "entities": {"description": {"urls": []}}, "followers_count": 46, "profile_sidebar_border_color": "C0DEED", "id_str": "2812367157", "profile_background_color": "C0DEED", "listed_count": 0, "is_translation_enabled": false, "utc_offset": null, "statuses_count": 242, "description": "Health Insurance Professional, Project Management, Volunteer, Hospitality Service, Wine Expert, Football Lover", "friends_count": 155, "location": "New Jersey,New York,California", "profile_link_color": "0084B4", "profile_image_url": "http://pbs.twimg.com/profile_images/519316499366825984/pL2NtKzZ_normal.jpeg", "following": null, "geo_enabled": true, "profile_banner_url": "https://pbs.twimg.com/profile_banners/2812367157/1412652325", "profile_background_image_url": "http://abs.twimg.com/images/themes/theme1/bg.png", "name": "Danielle", "lang": "en", "profile_background_tile": false, "favourites_count": 27, "screen_name": "dmarie818", "notifications": null, "url": null, "created_at": "Tue Oct 07 02:37:29 +0000 2014", "contributors_enabled": false, "time_zone": null, "protected": false, "default_profile": true, "is_translator": false}, "geo": {"type": "Point", "coordinates": [40.74639438, -74.0262015]}, "in_reply_to_user_id_str": null, "possibly_sensitive": false, "lang": "en", "created_at": "Mon Nov 17 19:01:20 +0000 2014", "in_reply_to_status_id_str": null, "place": {"country_code": "US", "url": "https://api.twitter.com/1.1/geo/id/e9143a85705b4d40.json", "country": "United States", "place_type": "city", "bounding_box": {"type": "Polygon", "coordinates": [[[-74.044085, 40.7336], [-74.020431, 40.7336], [-74.020431, 40.7591594], [-74.044085, 40.7591594]]]}, "contained_within": [], "full_name": "Hoboken, NJ", "attributes": {}, "id": "e9143a85705b4d40", "name": "Hoboken"}, "metadata": {"iso_language_code": "en", "result_type": "recent"}}, "data_point": "none", "user_location": "New Jersey,New York,California", "lon": 40.74639438, "content": "10 Craziest Things We Learned From the Aaliyah Lifetime Movie http://t.co/NgzGVq6ZFT via @rollingstone", "tweet_id": 534421044967522304, "user": 2812367157, "time": "Mon Nov 17 19:01:20 +0000 2014", "lat": -74.0262015}, "534421697928376320": {"raw_source": {"contributors": null, "truncated": false, "text": "\u201c@crystal_mojica: @njguido666 starter pack http://t.co/MB1lP3dUqW\u201d \ud83d\ude4f", "in_reply_to_status_id": 534419100769198080, "id": 534421697928376320, "favorite_count": 0, "source": "<a href=\"http://twitter.com/download/iphone\" rel=\"nofollow\">Twitter for iPhone</a>", "retweeted": false, "coordinates": {"type": "Point", "coordinates": [-74.00309753, 40.81373596]}, "entities": {"symbols": [], "user_mentions": [{"id": 2286773781, "indices": [1, 16], "id_str": "2286773781", "screen_name": "crystal_mojica", "name": "Crystal Mojica"}, {"id": 855271946, "indices": [18, 29], "id_str": "855271946", "screen_name": "njguido666", "name": "Alex Montero"}], "hashtags": [], "urls": [], "media": [{"source_status_id_str": "534419100769198080", "expanded_url": "http://twitter.com/crystal_mojica/status/534419100769198080/photo/1", "display_url": "pic.twitter.com/MB1lP3dUqW", "url": "http://t.co/MB1lP3dUqW", "media_url_https": "https://pbs.twimg.com/media/B2qjQQLIMAEe3Gn.jpg", "source_status_id": 534419100769198080, "id_str": "534419005411700737", "sizes": {"small": {"h": 328, "resize": "fit", "w": 340}, "large": {"h": 619, "resize": "fit", "w": 640}, "medium": {"h": 580, "resize": "fit", "w": 600}, "thumb": {"h": 150, "resize": "crop", "w": 150}}, "indices": [43, 65], "type": "photo", "id": 534419005411700737, "media_url": "http://pbs.twimg.com/media/B2qjQQLIMAEe3Gn.jpg"}]}, "in_reply_to_screen_name": "crystal_mojica", "in_reply_to_user_id": 2286773781, "retweet_count": 0, "id_str": "534421697928376320", "favorited": false, "user": {"follow_request_sent": null, "profile_use_background_image": true, "profile_text_color": "333333", "default_profile_image": false, "id": 855271946, "profile_background_image_url_https": "https://abs.twimg.com/images/themes/theme1/bg.png", "verified": false, "profile_location": null, "profile_image_url_https": "https://pbs.twimg.com/profile_images/519638955856109568/bI71rlIK_normal.jpeg", "profile_sidebar_fill_color": "DDEEF6", "entities": {"description": {"urls": []}}, "followers_count": 277, "profile_sidebar_border_color": "C0DEED", "id_str": "855271946", "profile_background_color": "C0DEED", "listed_count": 2, "is_translation_enabled": false, "utc_offset": -14400, "statuses_count": 10060, "description": "Low Life", "friends_count": 280, "location": "", "profile_link_color": "0084B4", "profile_image_url": "http://pbs.twimg.com/profile_images/519638955856109568/bI71rlIK_normal.jpeg", "following": null, "geo_enabled": true, "profile_banner_url": "https://pbs.twimg.com/profile_banners/855271946/1394654371", "profile_background_image_url": "http://abs.twimg.com/images/themes/theme1/bg.png", "name": "Alex Montero", "lang": "en", "profile_background_tile": false, "favourites_count": 7172, "screen_name": "njguido666", "notifications": null, "url": null, "created_at": "Sun Sep 30 19:57:21 +0000 2012", "contributors_enabled": false, "time_zone": "Atlantic Time (Canada)", "protected": false, "default_profile": true, "is_translator": false}, "geo": {"type": "Point", "coordinates": [40.81373596, -74.00309753]}, "in_reply_to_user_id_str": "2286773781", "possibly_sensitive": false, "lang": "en", "created_at": "Mon Nov 17 19:03:56 +0000 2014", "in_reply_to_status_id_str": "534419100769198080", "place": {"country_code": "US", "url": "https://api.twitter.com/1.1/geo/id/d7ce64e73b86c6f0.json", "country": "United States", "place_type": "city", "bounding_box": {"type": "Polygon", "coordinates": [[[-74.013771, 40.808433], [-73.9908176, 40.808433], [-73.9908176, 40.826826], [-74.013771, 40.826826]]]}, "contained_within": [], "full_name": "Fairview, NJ", "attributes": {}, "id": "d7ce64e73b86c6f0", "name": "Fairview"}, "metadata": {"iso_language_code": "en", "result_type": "recent"}}, "data_point": "none", "user_location": "", "lon": 40.81373596, "content": "\u201c@crystal_mojica: @njguido666 starter pack http://t.co/MB1lP3dUqW\u201d \ud83d\ude4f", "tweet_id": 534421697928376320, "user": 855271946, "time": "Mon Nov 17 19:03:56 +0000 2014", "lat": -74.00309753}, "534421701439004672": {"raw_source": {"contributors": null, "truncated": false, "text": "She wants to be my hero ain't use to the girl being the hero. But I need some saving.", "in_reply_to_status_id": null, "id": 534421701439004672, "favorite_count": 0, "source": "<a href=\"http://twitter.com/download/iphone\" rel=\"nofollow\">Twitter for iPhone</a>", "retweeted": false, "coordinates": {"type": "Point", "coordinates": [-73.87077171, 40.73439681]}, "entities": {"symbols": [], "user_mentions": [], "hashtags": [], "urls": []}, "in_reply_to_screen_name": null, "in_reply_to_user_id": null, "retweet_count": 0, "id_str": "534421701439004672", "favorited": false, "user": {"follow_request_sent": null, "profile_use_background_image": true, "profile_text_color": "333333", "default_profile_image": false, "id": 365894793, "profile_background_image_url_https": "https://pbs.twimg.com/profile_background_images/489677135934537729/7npenji_.jpeg", "verified": false, "profile_location": null, "profile_image_url_https": "https://pbs.twimg.com/profile_images/533763301889822720/bHDMiLL2_normal.jpeg", "profile_sidebar_fill_color": "DDEEF6", "entities": {"url": {"urls": [{"url": "http://t.co/yytL08TTfK", "indices": [0, 22], "expanded_url": "http://instagram.com/geeknerd85", "display_url": "instagram.com/geeknerd85"}]}, "description": {"urls": []}}, "followers_count": 429, "profile_sidebar_border_color": "000000", "id_str": "365894793", "profile_background_color": "C0DEED", "listed_count": 4, "is_translation_enabled": false, "utc_offset": -18000, "statuses_count": 6108, "description": "Just live life like tomorrow is your last. Live it with heart and energy. Leave the negative behind. It has no time in your life!!!", "friends_count": 1399, "location": "Where You From ", "profile_link_color": "1B0B8F", "profile_image_url": "http://pbs.twimg.com/profile_images/533763301889822720/bHDMiLL2_normal.jpeg", "following": null, "geo_enabled": true, "profile_banner_url": "https://pbs.twimg.com/profile_banners/365894793/1414809423", "profile_background_image_url": "http://pbs.twimg.com/profile_background_images/489677135934537729/7npenji_.jpeg", "name": "El Geek", "lang": "en", "profile_background_tile": false, "favourites_count": 403, "screen_name": "GeekNerd85", "notifications": null, "url": "http://t.co/yytL08TTfK", "created_at": "Thu Sep 01 06:04:20 +0000 2011", "contributors_enabled": false, "time_zone": "Eastern Time (US & Canada)", "protected": false, "default_profile": false, "is_translator": false}, "geo": {"type": "Point", "coordinates": [40.73439681, -73.87077171]}, "in_reply_to_user_id_str": null, "lang": "en", "created_at": "Mon Nov 17 19:03:57 +0000 2014", "in_reply_to_status_id_str": null, "place": {"country_code": "US", "url": "https://api.twitter.com/1.1/geo/id/00c39537733fa112.json", "country": "United States", "place_type": "city", "bounding_box": {"type": "Polygon", "coordinates": [[[-73.962582, 40.541722], [-73.699793, 40.541722], [-73.699793, 40.8000371], [-73.962582, 40.8000371]]]}, "contained_within": [], "full_name": "Queens, NY", "attributes": {}, "id": "00c39537733fa112", "name": "Queens"}, "metadata": {"iso_language_code": "en", "result_type": "recent"}}, "data_point": "none", "user_location": "Where You From ", "lon": 40.73439681, "content": "She wants to be my hero ain't use to the girl being the hero. But I need some saving.", "tweet_id": 534421701439004672, "user": 365894793, "time": "Mon Nov 17 19:03:57 +0000 2014", "lat": -73.87077171}, "534421699710574593": {"raw_source": {"contributors": null, "truncated": false, "text": "@archt_pilande @CodigoApps We build apps remotely! Our Portfolio \u261ehttp://t.co/yoNfd3pMVl let\u2019s talk :) Email to \u261e info@openwavecomp.com", "in_reply_to_status_id": 534218563720990720, "id": 534421699710574593, "favorite_count": 0, "source": "<a href=\"http://twitter.com\" rel=\"nofollow\">Twitter Web Client</a>", "retweeted": false, "coordinates": {"type": "Point", "coordinates": [0.0, 0.0]}, "entities": {"symbols": [], "user_mentions": [{"id": 238973111, "indices": [0, 14], "id_str": "238973111", "screen_name": "archt_pilande", "name": "James Paul Pilande"}, {"id": 173430343, "indices": [15, 26], "id_str": "173430343", "screen_name": "CodigoApps", "name": "Codigo"}], "hashtags": [], "urls": [{"url": "http://t.co/yoNfd3pMVl", "indices": [66, 88], "expanded_url": "http://x.co/5l22M", "display_url": "x.co/5l22M"}]}, "in_reply_to_screen_name": "archt_pilande", "in_reply_to_user_id": 238973111, "retweet_count": 0, "id_str": "534421699710574593", "favorited": false, "user": {"follow_request_sent": null, "profile_use_background_image": true, "profile_text_color": "333333", "default_profile_image": false, "id": 278011163, "profile_background_image_url_https": "https://pbs.twimg.com/profile_background_images/852037659/f704cc4764beaf45fd255beda3fc77b5.jpeg", "verified": false, "profile_location": null, "profile_image_url_https": "https://pbs.twimg.com/profile_images/1301932832/Openwave_normal.jpg", "profile_sidebar_fill_color": "DDEEF6", "entities": {"url": {"urls": [{"url": "http://t.co/hJz5PkKEvo", "indices": [0, 22], "expanded_url": "http://about.me/App_Developers_New_York", "display_url": "about.me/App_Developers\u2026"}]}, "description": {"urls": []}}, "followers_count": 648, "profile_sidebar_border_color": "FFFFFF", "id_str": "278011163", "profile_background_color": "C0DEED", "listed_count": 9, "is_translation_enabled": false, "utc_offset": -18000, "statuses_count": 3477, "description": "Openwave Computing LLC, NYC an ISO 9001: 2008 certified mobile app Development Company who are on demand now!! We make all sorts of apps for varied platforms!", "friends_count": 1586, "location": "New York", "profile_link_color": "0084B4", "profile_image_url": "http://pbs.twimg.com/profile_images/1301932832/Openwave_normal.jpg", "following": null, "geo_enabled": true, "profile_banner_url": "https://pbs.twimg.com/profile_banners/278011163/1398260309", "profile_background_image_url": "http://pbs.twimg.com/profile_background_images/852037659/f704cc4764beaf45fd255beda3fc77b5.jpeg", "name": "Apps Development NYC", "lang": "en", "profile_background_tile": false, "favourites_count": 171, "screen_name": "OWCServices", "notifications": null, "url": "http://t.co/hJz5PkKEvo", "created_at": "Wed Apr 06 12:38:17 +0000 2011", "contributors_enabled": false, "time_zone": "Eastern Time (US & Canada)", "protected": false, "default_profile": false, "is_translator": false}, "geo": {"type": "Point", "coordinates": [0.0, 0.0]}, "in_reply_to_user_id_str": "238973111", "possibly_sensitive": false, "lang": "en", "created_at": "Mon Nov 17 19:03:56 +0000 2014", "in_reply_to_status_id_str": "534218563720990720", "place": {"country_code": "US", "url": "https://api.twitter.com/1.1/geo/id/94965b2c45386f87.json", "country": "United States", "place_type": "admin", "bounding_box": {"type": "Polygon", "coordinates": [[[-79.76259, 40.477383], [-71.777492, 40.477383], [-71.777492, 45.015851], [-79.76259, 45.015851]]]}, "contained_within": [], "full_name": "New York, US", "attributes": {}, "id": "94965b2c45386f87", "name": "New York"}, "metadata": {"iso_language_code": "en", "result_type": "recent"}}, "data_point": "none", "user_location": "New York", "lon": 0.0, "content": "@archt_pilande @CodigoApps We build apps remotely! Our Portfolio \u261ehttp://t.co/yoNfd3pMVl let\u2019s talk :) Email to \u261e info@openwavecomp.com", "tweet_id": 534421699710574593, "user": 278011163, "time": "Mon Nov 17 19:03:56 +0000 2014", "lat": 0.0}, "534421706166009858": {"raw_source": {"contributors": null, "truncated": false, "text": "Thank you @Burberry for the raincoat. #nyc rain vortex.", "in_reply_to_status_id": null, "id": 534421706166009858, "favorite_count": 0, "source": "<a href=\"http://twitter.com/download/iphone\" rel=\"nofollow\">Twitter for iPhone</a>", "retweeted": false, "coordinates": {"type": "Point", "coordinates": [-73.97538766, 40.75538952]}, "entities": {"symbols": [], "user_mentions": [{"id": 47459700, "indices": [10, 19], "id_str": "47459700", "screen_name": "Burberry", "name": "Burberry"}], "hashtags": [{"indices": [38, 42], "text": "nyc"}], "urls": []}, "in_reply_to_screen_name": null, "in_reply_to_user_id": null, "retweet_count": 0, "id_str": "534421706166009858", "favorited": false, "user": {"follow_request_sent": null, "profile_use_background_image": true, "profile_text_color": "333333", "default_profile_image": false, "id": 38305834, "profile_background_image_url_https": "https://abs.twimg.com/images/themes/theme1/bg.png", "verified": false, "profile_location": null, "profile_image_url_https": "https://pbs.twimg.com/profile_images/479028066404937728/_WshFDkb_normal.jpeg", "profile_sidebar_fill_color": "DDEEF6", "entities": {"description": {"urls": []}}, "followers_count": 518, "profile_sidebar_border_color": "C0DEED", "id_str": "38305834", "profile_background_color": "C0DEED", "listed_count": 1, "is_translation_enabled": false, "utc_offset": -18000, "statuses_count": 1153, "description": "The Official Twitter Page of Faith  Fisher Einhorn", "friends_count": 750, "location": "New York", "profile_link_color": "2F88A8", "profile_image_url": "http://pbs.twimg.com/profile_images/479028066404937728/_WshFDkb_normal.jpeg", "following": null, "geo_enabled": true, "profile_banner_url": "https://pbs.twimg.com/profile_banners/38305834/1404856102", "profile_background_image_url": "http://abs.twimg.com/images/themes/theme1/bg.png", "name": "Faith Einhorn", "lang": "en", "profile_background_tile": false, "favourites_count": 318, "screen_name": "FaithEinhorn", "notifications": null, "url": null, "created_at": "Wed May 06 23:24:24 +0000 2009", "contributors_enabled": false, "time_zone": "Eastern Time (US & Canada)", "protected": false, "default_profile": false, "is_translator": false}, "geo": {"type": "Point", "coordinates": [40.75538952, -73.97538766]}, "in_reply_to_user_id_str": null, "lang": "en", "created_at": "Mon Nov 17 19:03:58 +0000 2014", "in_reply_to_status_id_str": null, "place": {"country_code": "US", "url": "https://api.twitter.com/1.1/geo/id/01a9a39529b27f36.json", "country": "United States", "place_type": "city", "bounding_box": {"type": "Polygon", "coordinates": [[[-74.026675, 40.683935], [-73.910408, 40.683935], [-73.910408, 40.877483], [-74.026675, 40.877483]]]}, "contained_within": [], "full_name": "Manhattan, NY", "attributes": {}, "id": "01a9a39529b27f36", "name": "Manhattan"}, "metadata": {"iso_language_code": "en", "result_type": "recent"}}, "data_point": "none", "user_location": "New York", "lon": 40.75538952, "content": "Thank you @Burberry for the raincoat. #nyc rain vortex.", "tweet_id": 534421706166009858, "user": 38305834, "time": "Mon Nov 17 19:03:58 +0000 2014", "lat": -73.97538766}, "534421171325124608": {"raw_source": {"contributors": null, "truncated": false, "text": "\"@kbrandtt: @m_scalici at least you know\" :(", "in_reply_to_status_id": null, "id": 534421171325124608, "favorite_count": 0, "source": "<a href=\"http://twitter.com/download/android\" rel=\"nofollow\">Twitter for Android</a>", "retweeted": false, "coordinates": {"type": "Point", "coordinates": [-74.0905423, 40.6173796]}, "entities": {"symbols": [], "user_mentions": [{"id": 603156082, "indices": [1, 10], "id_str": "603156082", "screen_name": "kbrandtt", "name": "Kyle Brandt"}, {"id": 1102567490, "indices": [12, 22], "id_str": "1102567490", "screen_name": "m_scalici", "name": "Stana Katic "}], "hashtags": [], "urls": []}, "in_reply_to_screen_name": null, "in_reply_to_user_id": null, "retweet_count": 0, "id_str": "534421171325124608", "favorited": false, "user": {"follow_request_sent": null, "profile_use_background_image": true, "profile_text_color": "000000", "default_profile_image": false, "id": 1102567490, "profile_background_image_url_https": "https://pbs.twimg.com/profile_background_images/815517068/da55aae3173ca09c676d03f09f733df1.png", "verified": false, "profile_location": null, "profile_image_url_https": "https://pbs.twimg.com/profile_images/532698819839143936/FcNZ6sf7_normal.jpeg", "profile_sidebar_fill_color": "FFFFFF", "entities": {"description": {"urls": []}}, "followers_count": 242, "profile_sidebar_border_color": "FFFFFF", "id_str": "1102567490", "profile_background_color": "FFFFFF", "listed_count": 0, "is_translation_enabled": false, "utc_offset": null, "statuses_count": 5411, "description": "Wagner College '18 student-athlete                                 #tracknation XC ; T&F ; Big Four Fan", "friends_count": 272, "location": "SI, NY.", "profile_link_color": "000000", "profile_image_url": "http://pbs.twimg.com/profile_images/532698819839143936/FcNZ6sf7_normal.jpeg", "following": null, "geo_enabled": true, "profile_banner_url": "https://pbs.twimg.com/profile_banners/1102567490/1415751896", "profile_background_image_url": "http://pbs.twimg.com/profile_background_images/815517068/da55aae3173ca09c676d03f09f733df1.png", "name": "Stana Katic ", "lang": "en", "profile_background_tile": true, "favourites_count": 638, "screen_name": "m_scalici", "notifications": null, "url": null, "created_at": "Sat Jan 19 02:21:50 +0000 2013", "contributors_enabled": false, "time_zone": null, "protected": false, "default_profile": false, "is_translator": false}, "geo": {"type": "Point", "coordinates": [40.6173796, -74.0905423]}, "in_reply_to_user_id_str": null, "lang": "en", "created_at": "Mon Nov 17 19:01:50 +0000 2014", "in_reply_to_status_id_str": null, "place": {"country_code": "US", "url": "https://api.twitter.com/1.1/geo/id/00c55f041e27dc51.json", "country": "United States", "place_type": "city", "bounding_box": {"type": "Polygon", "coordinates": [[[-74.255641, 40.495865], [-74.052253, 40.495865], [-74.052253, 40.648887], [-74.255641, 40.648887]]]}, "contained_within": [], "full_name": "Staten Island, NY", "attributes": {}, "id": "00c55f041e27dc51", "name": "Staten Island"}, "metadata": {"iso_language_code": "en", "result_type": "recent"}}, "data_point": "none", "user_location": "SI, NY.", "lon": 40.6173796, "content": "\"@kbrandtt: @m_scalici at least you know\" :(", "tweet_id": 534421171325124608, "user": 1102567490, "time": "Mon Nov 17 19:01:50 +0000 2014", "lat": -74.0905423}, "534421176924512256": {"raw_source": {"contributors": null, "truncated": false, "text": "@defpenradio Thanks! We also have an IOS app! Check it out", "in_reply_to_status_id": 534405718494150656, "id": 534421176924512256, "favorite_count": 0, "source": "<a href=\"http://twitter.com\" rel=\"nofollow\">Twitter Web Client</a>", "retweeted": false, "coordinates": {"type": "Point", "coordinates": [0.0, 0.0]}, "entities": {"symbols": [], "user_mentions": [{"id": 18650071, "indices": [0, 12], "id_str": "18650071", "screen_name": "defpenradio", "name": "Def Pen Radio\u2122"}], "hashtags": [], "urls": []}, "in_reply_to_screen_name": "defpenradio", "in_reply_to_user_id": 18650071, "retweet_count": 0, "id_str": "534421176924512256", "favorited": false, "user": {"follow_request_sent": null, "profile_use_background_image": true, "profile_text_color": "333333", "default_profile_image": false, "id": 1534857739, "profile_background_image_url_https": "https://pbs.twimg.com/profile_background_images/441654187298791424/AY-iczz_.png", "verified": false, "profile_location": null, "profile_image_url_https": "https://pbs.twimg.com/profile_images/459722184496148480/ngHkK4Cs_normal.png", "profile_sidebar_fill_color": "DDEEF6", "entities": {"url": {"urls": [{"url": "http://t.co/LSGFHrUTSm", "indices": [0, 22], "expanded_url": "http://www.sportchaser.com", "display_url": "sportchaser.com"}]}, "description": {"urls": [{"url": "http://t.co/pM6rYEQk2P", "indices": [126, 148], "expanded_url": "http://bit.ly/1xFQYXW", "display_url": "bit.ly/1xFQYXW"}]}}, "followers_count": 1645, "profile_sidebar_border_color": "FFFFFF", "id_str": "1534857739", "profile_background_color": "FF8400", "listed_count": 12, "is_translation_enabled": false, "utc_offset": -14400, "statuses_count": 4434, "description": "SportChaser is an online and mobile platform connecting sports fans to bars broadcasting their favorite games.      App link: http://t.co/pM6rYEQk2P", "friends_count": 1999, "location": "New York", "profile_link_color": "0084B4", "profile_image_url": "http://pbs.twimg.com/profile_images/459722184496148480/ngHkK4Cs_normal.png", "following": null, "geo_enabled": true, "profile_banner_url": "https://pbs.twimg.com/profile_banners/1534857739/1398439207", "profile_background_image_url": "http://pbs.twimg.com/profile_background_images/441654187298791424/AY-iczz_.png", "name": "SportChaser.com", "lang": "en", "profile_background_tile": false, "favourites_count": 1532, "screen_name": "SportChaser", "notifications": null, "url": "http://t.co/LSGFHrUTSm", "created_at": "Thu Jun 20 19:52:28 +0000 2013", "contributors_enabled": false, "time_zone": "Atlantic Time (Canada)", "protected": false, "default_profile": false, "is_translator": false}, "geo": {"type": "Point", "coordinates": [0.0, 0.0]}, "in_reply_to_user_id_str": "18650071", "lang": "en", "created_at": "Mon Nov 17 19:01:52 +0000 2014", "in_reply_to_status_id_str": "534405718494150656", "place": {"country_code": "US", "url": "https://api.twitter.com/1.1/geo/id/015e664c48444066.json", "country": "United States", "place_type": "city", "bounding_box": {"type": "Polygon", "coordinates": [[[-73.117153, 41.171997], [-72.990337, 41.171997], [-72.990337, 41.276059], [-73.117153, 41.276059]]]}, "contained_within": [], "full_name": "Milford, CT", "attributes": {}, "id": "015e664c48444066", "name": "Milford"}, "metadata": {"iso_language_code": "en", "result_type": "recent"}}, "data_point": "none", "user_location": "New York", "lon": 0.0, "content": "@defpenradio Thanks! We also have an IOS app! Check it out", "tweet_id": 534421176924512256, "user": 1534857739, "time": "Mon Nov 17 19:01:52 +0000 2014", "lat": 0.0}, "534420785579163648": {"raw_source": {"contributors": null, "truncated": false, "text": "I'm at Ellis Island Ferry Building in New York, NJ https://t.co/nnjseM3xjx", "in_reply_to_status_id": null, "id": 534420785579163648, "favorite_count": 0, "source": "<a href=\"http://foursquare.com\" rel=\"nofollow\">Foursquare</a>", "retweeted": false, "coordinates": {"type": "Point", "coordinates": [-74.03969228, 40.698686]}, "entities": {"symbols": [], "user_mentions": [], "hashtags": [], "urls": [{"url": "https://t.co/nnjseM3xjx", "indices": [51, 74], "expanded_url": "https://www.swarmapp.com/c/kpGRfuzQBYn", "display_url": "swarmapp.com/c/kpGRfuzQBYn"}]}, "in_reply_to_screen_name": null, "in_reply_to_user_id": null, "retweet_count": 0, "id_str": "534420785579163648", "favorited": false, "user": {"follow_request_sent": null, "profile_use_background_image": true, "profile_text_color": "333333", "default_profile_image": false, "id": 55700130, "profile_background_image_url_https": "https://abs.twimg.com/images/themes/theme1/bg.png", "verified": false, "profile_location": null, "profile_image_url_https": "https://pbs.twimg.com/profile_images/499290648986406912/dWK6VA2i_normal.jpeg", "profile_sidebar_fill_color": "DDEEF6", "entities": {"url": {"urls": [{"url": "http://t.co/2Yji1fF4TU", "indices": [0, 22], "expanded_url": "http://www.facebook.com/jplicqueiii", "display_url": "facebook.com/jplicqueiii"}]}, "description": {"urls": []}}, "followers_count": 584, "profile_sidebar_border_color": "C0DEED", "id_str": "55700130", "profile_background_color": "C0DEED", "listed_count": 5, "is_translation_enabled": false, "utc_offset": -18000, "statuses_count": 11516, "description": "#PMA Encouragor (not a word). Co-Creator/Prez of the Classy Fucking Gentlemen's Club. Lover of Anime, Wrestling, Comics, Video Games Jags/Yankees/Noles Diehard.", "friends_count": 1776, "location": "Jacksonville, FL", "profile_link_color": "0084B4", "profile_image_url": "http://pbs.twimg.com/profile_images/499290648986406912/dWK6VA2i_normal.jpeg", "following": null, "geo_enabled": true, "profile_banner_url": "https://pbs.twimg.com/profile_banners/55700130/1356042929", "profile_background_image_url": "http://abs.twimg.com/images/themes/theme1/bg.png", "name": "Jacob A. Plicque III", "lang": "en", "profile_background_tile": false, "favourites_count": 807, "screen_name": "EXPReaperJabub", "notifications": null, "url": "http://t.co/2Yji1fF4TU", "created_at": "Fri Jul 10 23:44:10 +0000 2009", "contributors_enabled": false, "time_zone": "Eastern Time (US & Canada)", "protected": false, "default_profile": true, "is_translator": false}, "geo": {"type": "Point", "coordinates": [40.698686, -74.03969228]}, "in_reply_to_user_id_str": null, "possibly_sensitive": false, "lang": "en", "created_at": "Mon Nov 17 19:00:18 +0000 2014", "in_reply_to_status_id_str": null, "place": {"country_code": "US", "url": "https://api.twitter.com/1.1/geo/id/65b4760a2b411e11.json", "country": "United States", "place_type": "admin", "bounding_box": {"type": "Polygon", "coordinates": [[[-75.563587, 38.788657], [-73.88506, 38.788657], [-73.88506, 41.357424], [-75.563587, 41.357424]]]}, "contained_within": [], "full_name": "New Jersey, US", "attributes": {}, "id": "65b4760a2b411e11", "name": "New Jersey"}, "metadata": {"iso_language_code": "en", "result_type": "recent"}}, "data_point": "none", "user_location": "Jacksonville, FL", "lon": 40.698686, "content": "I'm at Ellis Island Ferry Building in New York, NJ https://t.co/nnjseM3xjx", "tweet_id": 534420785579163648, "user": 55700130, "time": "Mon Nov 17 19:00:18 +0000 2014", "lat": -74.03969228}, "534421176794480642": {"raw_source": {"contributors": null, "truncated": false, "text": "@HumbleTeej Of course. It is. Snow is magical and reflects the lights!", "in_reply_to_status_id": 534421017033076736, "id": 534421176794480642, "favorite_count": 0, "source": "<a href=\"http://twitter.com/download/iphone\" rel=\"nofollow\">Twitter for iPhone</a>", "retweeted": false, "coordinates": {"type": "Point", "coordinates": [-74.01194781, 40.70236367]}, "entities": {"symbols": [], "user_mentions": [{"id": 20290012, "indices": [0, 11], "id_str": "20290012", "screen_name": "HumbleTeej", "name": "#BoneInRibeyeGawd"}], "hashtags": [], "urls": []}, "in_reply_to_screen_name": "HumbleTeej", "in_reply_to_user_id": 20290012, "retweet_count": 0, "id_str": "534421176794480642", "favorited": false, "user": {"follow_request_sent": null, "profile_use_background_image": true, "profile_text_color": "333333", "default_profile_image": false, "id": 29536550, "profile_background_image_url_https": "https://pbs.twimg.com/profile_background_images/98272990/3698331020a.jpg", "verified": false, "profile_location": null, "profile_image_url_https": "https://pbs.twimg.com/profile_images/531783493148098560/tFnVtcyZ_normal.jpeg", "profile_sidebar_fill_color": "DDEEF6", "entities": {"description": {"urls": []}}, "followers_count": 1005, "profile_sidebar_border_color": "C0DEED", "id_str": "29536550", "profile_background_color": "C0DEED", "listed_count": 35, "is_translation_enabled": false, "utc_offset": -18000, "statuses_count": 40956, "description": "Writer, Schadenfreude Connoisseur, Hip Hop Aficionado, General Malcontent. I'm a @PassionWeiss Guy.", "friends_count": 679, "location": "Brooklyn, NY", "profile_link_color": "0084B4", "profile_image_url": "http://pbs.twimg.com/profile_images/531783493148098560/tFnVtcyZ_normal.jpeg", "following": null, "geo_enabled": true, "profile_background_image_url": "http://pbs.twimg.com/profile_background_images/98272990/3698331020a.jpg", "name": "B.J. Steiner", "lang": "en", "profile_background_tile": true, "favourites_count": 371, "screen_name": "DocZeus", "notifications": null, "url": null, "created_at": "Tue Apr 07 20:30:15 +0000 2009", "contributors_enabled": false, "time_zone": "Eastern Time (US & Canada)", "protected": false, "default_profile": false, "is_translator": false}, "geo": {"type": "Point", "coordinates": [40.70236367, -74.01194781]}, "in_reply_to_user_id_str": "20290012", "lang": "en", "created_at": "Mon Nov 17 19:01:52 +0000 2014", "in_reply_to_status_id_str": "534421017033076736", "place": {"country_code": "US", "url": "https://api.twitter.com/1.1/geo/id/01a9a39529b27f36.json", "country": "United States", "place_type": "city", "bounding_box": {"type": "Polygon", "coordinates": [[[-74.026675, 40.683935], [-73.910408, 40.683935], [-73.910408, 40.877483], [-74.026675, 40.877483]]]}, "contained_within": [], "full_name": "Manhattan, NY", "attributes": {}, "id": "01a9a39529b27f36", "name": "Manhattan"}, "metadata": {"iso_language_code": "en", "result_type": "recent"}}, "data_point": "none", "user_location": "Brooklyn, NY", "lon": 40.70236367, "content": "@HumbleTeej Of course. It is. Snow is magical and reflects the lights!", "tweet_id": 534421176794480642, "user": 29536550, "time": "Mon Nov 17 19:01:52 +0000 2014", "lat": -74.01194781}, "534420643773939712": {"raw_source": {"contributors": null, "truncated": false, "text": "Q1: Which #OUT100 2014 profile on http://t.co/U8827C1iBo resonated most with you &amp; why?", "in_reply_to_status_id": null, "id": 534420643773939712, "favorite_count": 0, "source": "<a href=\"http://twitter.com\" rel=\"nofollow\">Twitter Web Client</a>", "retweeted": false, "coordinates": {"type": "Point", "coordinates": [0.0, 0.0]}, "entities": {"symbols": [], "user_mentions": [], "hashtags": [{"indices": [10, 17], "text": "OUT100"}], "urls": [{"url": "http://t.co/U8827C1iBo", "indices": [34, 56], "expanded_url": "http://Out.com", "display_url": "Out.com"}]}, "in_reply_to_screen_name": null, "in_reply_to_user_id": null, "retweet_count": 0, "id_str": "534420643773939712", "favorited": false, "user": {"follow_request_sent": null, "profile_use_background_image": false, "profile_text_color": "333333", "default_profile_image": false, "id": 21713274, "profile_background_image_url_https": "https://pbs.twimg.com/profile_background_images/453573944042201088/whRCwLdW.jpeg", "verified": false, "profile_location": null, "profile_image_url_https": "https://pbs.twimg.com/profile_images/458734089592246272/QOGF4XtX_normal.jpeg", "profile_sidebar_fill_color": "DDEEF6", "entities": {"url": {"urls": [{"url": "http://t.co/qSvptKrqCj", "indices": [0, 22], "expanded_url": "http://www.out.com", "display_url": "out.com"}]}, "description": {"urls": []}}, "followers_count": 97567, "profile_sidebar_border_color": "FFFFFF", "id_str": "21713274", "profile_background_color": "FFFFFF", "listed_count": 1761, "is_translation_enabled": false, "utc_offset": -18000, "statuses_count": 18446, "description": "The World\u2019s Leading Gay Fashion & Lifestyle Brand", "friends_count": 1279, "location": "New York, NY", "profile_link_color": "990000", "profile_image_url": "http://pbs.twimg.com/profile_images/458734089592246272/QOGF4XtX_normal.jpeg", "following": null, "geo_enabled": true, "profile_banner_url": "https://pbs.twimg.com/profile_banners/21713274/1415992436", "profile_background_image_url": "http://pbs.twimg.com/profile_background_images/453573944042201088/whRCwLdW.jpeg", "name": "Out Magazine", "lang": "en", "profile_background_tile": false, "favourites_count": 587, "screen_name": "outmagazine", "notifications": null, "url": "http://t.co/qSvptKrqCj", "created_at": "Tue Feb 24 00:43:12 +0000 2009", "contributors_enabled": false, "time_zone": "Eastern Time (US & Canada)", "protected": false, "default_profile": false, "is_translator": false}, "geo": {"type": "Point", "coordinates": [0.0, 0.0]}, "in_reply_to_user_id_str": null, "possibly_sensitive": false, "lang": "en", "created_at": "Mon Nov 17 18:59:45 +0000 2014", "in_reply_to_status_id_str": null, "place": {"country_code": "US", "url": "https://api.twitter.com/1.1/geo/id/3b77caf94bfc81fe.json", "country": "United States", "place_type": "city", "bounding_box": {"type": "Polygon", "coordinates": [[[-118.668404, 33.704538], [-118.155409, 33.704538], [-118.155409, 34.337041], [-118.668404, 34.337041]]]}, "contained_within": [], "full_name": "Los Angeles, CA", "attributes": {}, "id": "3b77caf94bfc81fe", "name": "Los Angeles"}, "metadata": {"iso_language_code": "en", "result_type": "recent"}}, "data_point": "none", "user_location": "New York, NY", "lon": 0.0, "content": "Q1: Which #OUT100 2014 profile on http://t.co/U8827C1iBo resonated most with you &amp; why?", "tweet_id": 534420643773939712, "user": 21713274, "time": "Mon Nov 17 18:59:45 +0000 2014", "lat": 0.0}, "534421795219456000": {"raw_source": {"contributors": null, "truncated": false, "text": "Loving these Anabel Higgins' pieces! #gemcandy #silver @jckmagazine @ New York City http://t.co/24HPGnWveh", "in_reply_to_status_id": null, "id": 534421795219456000, "favorite_count": 0, "source": "<a href=\"http://instagram.com\" rel=\"nofollow\">Instagram</a>", "retweeted": false, "coordinates": {"type": "Point", "coordinates": [-73.99467539, 40.74891344]}, "entities": {"symbols": [], "user_mentions": [{"id": 46216048, "indices": [55, 67], "id_str": "46216048", "screen_name": "JCKMagazine", "name": "JCK Magazine"}], "hashtags": [{"indices": [37, 46], "text": "gemcandy"}, {"indices": [47, 54], "text": "silver"}], "urls": [{"url": "http://t.co/24HPGnWveh", "indices": [84, 106], "expanded_url": "http://instagram.com/p/vgwwLpDw3I/", "display_url": "instagram.com/p/vgwwLpDw3I/"}]}, "in_reply_to_screen_name": null, "in_reply_to_user_id": null, "retweet_count": 0, "id_str": "534421795219456000", "favorited": false, "user": {"follow_request_sent": null, "profile_use_background_image": true, "profile_text_color": "333333", "default_profile_image": false, "id": 15151307, "profile_background_image_url_https": "https://pbs.twimg.com/profile_background_images/666485454/ed7b4f2c5ac947db5b61fbc08e7c2298.jpeg", "verified": false, "profile_location": null, "profile_image_url_https": "https://pbs.twimg.com/profile_images/2634257292/ef4a461d04c8850840e1e2d4d2c4c47b_normal.png", "profile_sidebar_fill_color": "DDEEF6", "entities": {"url": {"urls": [{"url": "http://t.co/aMcnpzZoXB", "indices": [0, 22], "expanded_url": "http://www.jckonline.com/blogs/style-360", "display_url": "jckonline.com/blogs/style-360"}]}, "description": {"urls": []}}, "followers_count": 7408, "profile_sidebar_border_color": "FFFFFF", "id_str": "15151307", "profile_background_color": "FFF04D", "listed_count": 181, "is_translation_enabled": false, "utc_offset": -18000, "statuses_count": 2972, "description": "Jewelry Journalist & Market Editor, Blogger, JCK Magazine Senior Editor", "friends_count": 3328, "location": "New York City", "profile_link_color": "0099CC", "profile_image_url": "http://pbs.twimg.com/profile_images/2634257292/ef4a461d04c8850840e1e2d4d2c4c47b_normal.png", "following": null, "geo_enabled": true, "profile_background_image_url": "http://pbs.twimg.com/profile_background_images/666485454/ed7b4f2c5ac947db5b61fbc08e7c2298.jpeg", "name": "Jennifer Heebner", "lang": "en", "profile_background_tile": true, "favourites_count": 93, "screen_name": "jenniferheebner", "notifications": null, "url": "http://t.co/aMcnpzZoXB", "created_at": "Tue Jun 17 22:48:51 +0000 2008", "contributors_enabled": false, "time_zone": "Eastern Time (US & Canada)", "protected": false, "default_profile": false, "is_translator": false}, "geo": {"type": "Point", "coordinates": [40.74891344, -73.99467539]}, "in_reply_to_user_id_str": null, "possibly_sensitive": false, "lang": "en", "created_at": "Mon Nov 17 19:04:19 +0000 2014", "in_reply_to_status_id_str": null, "place": {"country_code": "US", "url": "https://api.twitter.com/1.1/geo/id/01a9a39529b27f36.json", "country": "United States", "place_type": "city", "bounding_box": {"type": "Polygon", "coordinates": [[[-74.026675, 40.683935], [-73.910408, 40.683935], [-73.910408, 40.877483], [-74.026675, 40.877483]]]}, "contained_within": [], "full_name": "Manhattan, NY", "attributes": {}, "id": "01a9a39529b27f36", "name": "Manhattan"}, "metadata": {"iso_language_code": "en", "result_type": "recent"}}, "data_point": "none", "user_location": "New York City", "lon": 40.74891344, "content": "Loving these Anabel Higgins' pieces! #gemcandy #silver @jckmagazine @ New York City http://t.co/24HPGnWveh", "tweet_id": 534421795219456000, "user": 15151307, "time": "Mon Nov 17 19:04:19 +0000 2014", "lat": -73.99467539}, "534421698414526464": {"raw_source": {"contributors": null, "truncated": false, "text": "@dakminx good afternoon!", "in_reply_to_status_id": 534391066170908673, "id": 534421698414526464, "favorite_count": 0, "source": "<a href=\"http://twitter.com/download/iphone\" rel=\"nofollow\">Twitter for iPhone</a>", "retweeted": false, "coordinates": {"type": "Point", "coordinates": [-73.98031611, 40.76070718]}, "entities": {"symbols": [], "user_mentions": [{"id": 44513266, "indices": [0, 8], "id_str": "44513266", "screen_name": "dakminx", "name": "SchaMyn"}], "hashtags": [], "urls": []}, "in_reply_to_screen_name": "dakminx", "in_reply_to_user_id": 44513266, "retweet_count": 0, "id_str": "534421698414526464", "favorited": false, "user": {"follow_request_sent": null, "profile_use_background_image": true, "profile_text_color": "520C2E", "default_profile_image": false, "id": 107583914, "profile_background_image_url_https": "https://pbs.twimg.com/profile_background_images/378800000148035544/Q_ueFRlD.jpeg", "verified": false, "profile_location": null, "profile_image_url_https": "https://pbs.twimg.com/profile_images/531851895598768128/br5kZblP_normal.jpeg", "profile_sidebar_fill_color": "E3BBB6", "entities": {"url": {"urls": [{"url": "http://t.co/8GDfPJpgAo", "indices": [0, 22], "expanded_url": "http://www.instagram.com/onedaniella", "display_url": "instagram.com/onedaniella"}]}, "description": {"urls": []}}, "followers_count": 32159, "profile_sidebar_border_color": "FFFFFF", "id_str": "107583914", "profile_background_color": "24D4D4", "listed_count": 43, "is_translation_enabled": false, "utc_offset": -18000, "statuses_count": 6388, "description": "Provoker, disrupter and maker. #Rubyist #Bitcoiner #Chairwoman  Klout 78. DF/BOS/NY", "friends_count": 144, "location": "onedaniella@hotmail.com", "profile_link_color": "FFCC4D", "profile_image_url": "http://pbs.twimg.com/profile_images/531851895598768128/br5kZblP_normal.jpeg", "following": null, "geo_enabled": true, "profile_banner_url": "https://pbs.twimg.com/profile_banners/107583914/1415420575", "profile_background_image_url": "http://pbs.twimg.com/profile_background_images/378800000148035544/Q_ueFRlD.jpeg", "name": "OneDaniella", "lang": "en", "profile_background_tile": false, "favourites_count": 3285, "screen_name": "theonedaniella", "notifications": null, "url": "http://t.co/8GDfPJpgAo", "created_at": "Sat Jan 23 02:02:08 +0000 2010", "contributors_enabled": false, "time_zone": "Eastern Time (US & Canada)", "protected": false, "default_profile": false, "is_translator": false}, "geo": {"type": "Point", "coordinates": [40.76070718, -73.98031611]}, "in_reply_to_user_id_str": "44513266", "lang": "en", "created_at": "Mon Nov 17 19:03:56 +0000 2014", "in_reply_to_status_id_str": "534391066170908673", "place": {"country_code": "US", "url": "https://api.twitter.com/1.1/geo/id/01a9a39529b27f36.json", "country": "United States", "place_type": "city", "bounding_box": {"type": "Polygon", "coordinates": [[[-74.026675, 40.683935], [-73.910408, 40.683935], [-73.910408, 40.877483], [-74.026675, 40.877483]]]}, "contained_within": [], "full_name": "Manhattan, NY", "attributes": {}, "id": "01a9a39529b27f36", "name": "Manhattan"}, "metadata": {"iso_language_code": "en", "result_type": "recent"}}, "data_point": "none", "user_location": "onedaniella@hotmail.com", "lon": 40.76070718, "content": "@dakminx good afternoon!", "tweet_id": 534421698414526464, "user": 107583914, "time": "Mon Nov 17 19:03:56 +0000 2014", "lat": -73.98031611}, "534421805545844736": {"raw_source": {"contributors": null, "truncated": false, "text": "@naturallysavvy #boironlearn as a teacher I salute you for a non drug remedy!", "in_reply_to_status_id": null, "id": 534421805545844736, "favorite_count": 0, "source": "<a href=\"http://twitter.com\" rel=\"nofollow\">Twitter Web Client</a>", "retweeted": false, "coordinates": {"type": "Point", "coordinates": [0.0, 0.0]}, "entities": {"symbols": [], "user_mentions": [{"id": 14469246, "indices": [0, 15], "id_str": "14469246", "screen_name": "naturallysavvy", "name": "Naturally Savvy"}], "hashtags": [{"indices": [16, 28], "text": "boironlearn"}], "urls": []}, "in_reply_to_screen_name": "naturallysavvy", "in_reply_to_user_id": 14469246, "retweet_count": 1, "id_str": "534421805545844736", "favorited": false, "user": {"follow_request_sent": null, "profile_use_background_image": true, "profile_text_color": "4CCACF", "default_profile_image": false, "id": 35033769, "profile_background_image_url_https": "https://pbs.twimg.com/profile_background_images/457395412656091136/QQVuyMqi.png", "verified": false, "profile_location": null, "profile_image_url_https": "https://pbs.twimg.com/profile_images/520674489843986432/GM8jj6Dm_normal.jpeg", "profile_sidebar_fill_color": "3BB3B8", "entities": {"url": {"urls": [{"url": "http://t.co/8e5u5ANw4y", "indices": [0, 22], "expanded_url": "http://www.freewebs.com/correytravel/", "display_url": "freewebs.com/correytravel/"}]}, "description": {"urls": []}}, "followers_count": 977, "profile_sidebar_border_color": "FFFFFF", "id_str": "35033769", "profile_background_color": "161617", "listed_count": 17, "is_translation_enabled": false, "utc_offset": -18000, "statuses_count": 15711, "description": "Mom of 2, Teacher for Special ed, Blogger for Education & Travel. Booking a trip? You got the perfect expert to do it.  Travel Consultant for 30+ years.\u2764\ufe0f", "friends_count": 1392, "location": "Brooklyn, NY", "profile_link_color": "89C9FA", "profile_image_url": "http://pbs.twimg.com/profile_images/520674489843986432/GM8jj6Dm_normal.jpeg", "following": null, "geo_enabled": true, "profile_banner_url": "https://pbs.twimg.com/profile_banners/35033769/1409126052", "profile_background_image_url": "http://pbs.twimg.com/profile_background_images/457395412656091136/QQVuyMqi.png", "name": "Correy's Time2Travel", "lang": "en", "profile_background_tile": true, "favourites_count": 345, "screen_name": "CorreyHope", "notifications": null, "url": "http://t.co/8e5u5ANw4y", "created_at": "Fri Apr 24 20:42:20 +0000 2009", "contributors_enabled": false, "time_zone": "Eastern Time (US & Canada)", "protected": false, "default_profile": false, "is_translator": false}, "geo": {"type": "Point", "coordinates": [0.0, 0.0]}, "in_reply_to_user_id_str": "14469246", "lang": "en", "created_at": "Mon Nov 17 19:04:22 +0000 2014", "in_reply_to_status_id_str": null, "place": {"country_code": "US", "url": "https://api.twitter.com/1.1/geo/id/011add077f4d2da3.json", "country": "United States", "place_type": "city", "bounding_box": {"type": "Polygon", "coordinates": [[[-74.041878, 40.570842], [-73.855673, 40.570842], [-73.855673, 40.739434], [-74.041878, 40.739434]]]}, "contained_within": [], "full_name": "Brooklyn, NY", "attributes": {}, "id": "011add077f4d2da3", "name": "Brooklyn"}, "metadata": {"iso_language_code": "en", "result_type": "recent"}}, "data_point": "none", "user_location": "Brooklyn, NY", "lon": 0.0, "content": "@naturallysavvy #boironlearn as a teacher I salute you for a non drug remedy!", "tweet_id": 534421805545844736, "user": 35033769, "time": "Mon Nov 17 19:04:22 +0000 2014", "lat": 0.0}, "534421300417413120": {"raw_source": {"contributors": null, "truncated": false, "text": "Listening to @HendreCoetzee talk about the unprecedented future' to 'depersonalize your resistance.' #NewWayToWork http://t.co/PP5oUHDZ4w", "in_reply_to_status_id": null, "id": 534421300417413120, "favorite_count": 0, "source": "<a href=\"http://twitter.com/download/iphone\" rel=\"nofollow\">Twitter for iPhone</a>", "retweeted": false, "coordinates": {"type": "Point", "coordinates": [-73.99008149, 40.73685363]}, "entities": {"symbols": [], "user_mentions": [{"id": 253817095, "indices": [13, 27], "id_str": "253817095", "screen_name": "HendreCoetzee", "name": "Hendre Coetzee"}], "hashtags": [{"indices": [101, 114], "text": "NewWayToWork"}], "urls": [], "media": [{"expanded_url": "http://twitter.com/dhinchcliffe/status/534421300417413120/photo/1", "display_url": "pic.twitter.com/PP5oUHDZ4w", "url": "http://t.co/PP5oUHDZ4w", "media_url_https": "https://pbs.twimg.com/media/B2qlVKvIQAEHoOV.jpg", "id_str": "534421288874688513", "sizes": {"small": {"h": 255, "resize": "fit", "w": 340}, "large": {"h": 768, "resize": "fit", "w": 1024}, "medium": {"h": 450, "resize": "fit", "w": 600}, "thumb": {"h": 150, "resize": "crop", "w": 150}}, "indices": [115, 137], "type": "photo", "id": 534421288874688513, "media_url": "http://pbs.twimg.com/media/B2qlVKvIQAEHoOV.jpg"}]}, "in_reply_to_screen_name": null, "in_reply_to_user_id": null, "retweet_count": 0, "id_str": "534421300417413120", "favorited": false, "user": {"follow_request_sent": null, "profile_use_background_image": true, "profile_text_color": "000000", "default_profile_image": false, "id": 1585, "profile_background_image_url_https": "https://pbs.twimg.com/profile_background_images/448487105669234688/ckrPSRrk.png", "verified": false, "profile_location": null, "profile_image_url_https": "https://pbs.twimg.com/profile_images/2228251926/dion_headshot_red_background_normal.jpg", "profile_sidebar_fill_color": "E0FF92", "entities": {"url": {"urls": [{"url": "http://t.co/s9pKoQ7Gtl", "indices": [0, 22], "expanded_url": "http://adjuvi.com", "display_url": "adjuvi.com"}]}, "description": {"urls": []}}, "followers_count": 28252, "profile_sidebar_border_color": "FFFFFF", "id_str": "1585", "profile_background_color": "000000", "listed_count": 2703, "is_translation_enabled": false, "utc_offset": -18000, "statuses_count": 15945, "description": "Chief Strategy Officer, business strategist, enterprise architect, keynote speaker, book author, blogger, & consultant on #socbiz & next-gen enterprises.", "friends_count": 1277, "location": "Washington, D.C.", "profile_link_color": "333370", "profile_image_url": "http://pbs.twimg.com/profile_images/2228251926/dion_headshot_red_background_normal.jpg", "following": null, "geo_enabled": true, "profile_background_image_url": "http://pbs.twimg.com/profile_background_images/448487105669234688/ckrPSRrk.png", "name": "Dion Hinchcliffe", "lang": "en", "profile_background_tile": false, "favourites_count": 3157, "screen_name": "dhinchcliffe", "notifications": null, "url": "http://t.co/s9pKoQ7Gtl", "created_at": "Sun Jul 16 21:38:36 +0000 2006", "contributors_enabled": false, "time_zone": "Eastern Time (US & Canada)", "protected": false, "default_profile": false, "is_translator": false}, "geo": {"type": "Point", "coordinates": [40.73685363, -73.99008149]}, "in_reply_to_user_id_str": null, "possibly_sensitive": false, "lang": "en", "created_at": "Mon Nov 17 19:02:21 +0000 2014", "in_reply_to_status_id_str": null, "place": {"country_code": "US", "url": "https://api.twitter.com/1.1/geo/id/01a9a39529b27f36.json", "country": "United States", "place_type": "city", "bounding_box": {"type": "Polygon", "coordinates": [[[-74.026675, 40.683935], [-73.910408, 40.683935], [-73.910408, 40.877483], [-74.026675, 40.877483]]]}, "contained_within": [], "full_name": "Manhattan, NY", "attributes": {}, "id": "01a9a39529b27f36", "name": "Manhattan"}, "metadata": {"iso_language_code": "en", "result_type": "recent"}}, "data_point": "none", "user_location": "Washington, D.C.", "lon": 40.73685363, "content": "Listening to @HendreCoetzee talk about the unprecedented future' to 'depersonalize your resistance.' #NewWayToWork http://t.co/PP5oUHDZ4w", "tweet_id": 534421300417413120, "user": 1585, "time": "Mon Nov 17 19:02:21 +0000 2014", "lat": -73.99008149}, "534421303026286593": {"raw_source": {"contributors": null, "truncated": false, "text": "@itsDelaneSean Oo okay lmao\ud83d\ude2c", "in_reply_to_status_id": 534420890453569536, "id": 534421303026286593, "favorite_count": 1, "source": "<a href=\"http://twitter.com/download/iphone\" rel=\"nofollow\">Twitter for iPhone</a>", "retweeted": false, "coordinates": {"type": "Point", "coordinates": [-74.06303535, 40.73036679]}, "entities": {"symbols": [], "user_mentions": [{"id": 328851914, "indices": [0, 14], "id_str": "328851914", "screen_name": "itsDelaneSean", "name": "LANE"}], "hashtags": [], "urls": []}, "in_reply_to_screen_name": "itsDelaneSean", "in_reply_to_user_id": 328851914, "retweet_count": 0, "id_str": "534421303026286593", "favorited": false, "user": {"follow_request_sent": null, "profile_use_background_image": true, "profile_text_color": "333333", "default_profile_image": false, "id": 489660028, "profile_background_image_url_https": "https://abs.twimg.com/images/themes/theme14/bg.gif", "verified": false, "profile_location": null, "profile_image_url_https": "https://pbs.twimg.com/profile_images/531689213931315200/qNJq2pk2_normal.jpeg", "profile_sidebar_fill_color": "EFEFEF", "entities": {"description": {"urls": []}}, "followers_count": 579, "profile_sidebar_border_color": "EEEEEE", "id_str": "489660028", "profile_background_color": "131516", "listed_count": 0, "is_translation_enabled": false, "utc_offset": -18000, "statuses_count": 10201, "description": "\u2022sicker than your average\u2022           Instaaaaa:@_hannan", "friends_count": 451, "location": "", "profile_link_color": "009999", "profile_image_url": "http://pbs.twimg.com/profile_images/531689213931315200/qNJq2pk2_normal.jpeg", "following": null, "geo_enabled": true, "profile_banner_url": "https://pbs.twimg.com/profile_banners/489660028/1414073519", "profile_background_image_url": "http://abs.twimg.com/images/themes/theme14/bg.gif", "name": "Haannn", "lang": "en", "profile_background_tile": true, "favourites_count": 1428, "screen_name": "hannanelzoghabi", "notifications": null, "url": null, "created_at": "Sat Feb 11 19:12:18 +0000 2012", "contributors_enabled": false, "time_zone": "Eastern Time (US & Canada)", "protected": false, "default_profile": false, "is_translator": false}, "geo": {"type": "Point", "coordinates": [40.73036679, -74.06303535]}, "in_reply_to_user_id_str": "328851914", "lang": "ht", "created_at": "Mon Nov 17 19:02:22 +0000 2014", "in_reply_to_status_id_str": "534420890453569536", "place": {"country_code": "US", "url": "https://api.twitter.com/1.1/geo/id/b046074b1030a44d.json", "country": "United States", "place_type": "city", "bounding_box": {"type": "Polygon", "coordinates": [[[-74.107995, 40.666879], [-74.0253309, 40.666879], [-74.0253309, 40.769124], [-74.107995, 40.769124]]]}, "contained_within": [], "full_name": "Jersey City, NJ", "attributes": {}, "id": "b046074b1030a44d", "name": "Jersey City"}, "metadata": {"iso_language_code": "ht", "result_type": "recent"}}, "data_point": "none", "user_location": "", "lon": 40.73036679, "content": "@itsDelaneSean Oo okay lmao\ud83d\ude2c", "tweet_id": 534421303026286593, "user": 489660028, "time": "Mon Nov 17 19:02:22 +0000 2014", "lat": -74.06303535}, "534421307681951744": {"raw_source": {"contributors": null, "truncated": false, "text": "I'm at @Google New York in New York, NY https://t.co/27poYMlX27", "in_reply_to_status_id": null, "id": 534421307681951744, "favorite_count": 0, "source": "<a href=\"http://foursquare.com\" rel=\"nofollow\">Foursquare</a>", "retweeted": false, "coordinates": {"type": "Point", "coordinates": [-74.00331557, 40.7414688]}, "entities": {"symbols": [], "user_mentions": [{"id": 20536157, "indices": [7, 14], "id_str": "20536157", "screen_name": "google", "name": "Google"}], "hashtags": [], "urls": [{"url": "https://t.co/27poYMlX27", "indices": [40, 63], "expanded_url": "https://www.swarmapp.com/c/7MJAMRV7lUs", "display_url": "swarmapp.com/c/7MJAMRV7lUs"}]}, "in_reply_to_screen_name": null, "in_reply_to_user_id": null, "retweet_count": 0, "id_str": "534421307681951744", "favorited": false, "user": {"follow_request_sent": null, "profile_use_background_image": true, "profile_text_color": "333333", "default_profile_image": false, "id": 355701353, "profile_background_image_url_https": "https://abs.twimg.com/images/themes/theme1/bg.png", "verified": false, "profile_location": null, "profile_image_url_https": "https://pbs.twimg.com/profile_images/503308383013715969/ki3h-Mq9_normal.jpeg", "profile_sidebar_fill_color": "DDEEF6", "entities": {"description": {"urls": []}}, "followers_count": 361, "profile_sidebar_border_color": "C0DEED", "id_str": "355701353", "profile_background_color": "C0DEED", "listed_count": 2, "is_translation_enabled": false, "utc_offset": 7200, "statuses_count": 6997, "description": "\u00c7ok afedersiniz g\u00e2vur - Istanbul", "friends_count": 818, "location": "Izmir Ankara Madrid Dublin", "profile_link_color": "B30000", "profile_image_url": "http://pbs.twimg.com/profile_images/503308383013715969/ki3h-Mq9_normal.jpeg", "following": null, "geo_enabled": true, "profile_banner_url": "https://pbs.twimg.com/profile_banners/355701353/1408387612", "profile_background_image_url": "http://abs.twimg.com/images/themes/theme1/bg.png", "name": "Minima", "lang": "en", "profile_background_tile": false, "favourites_count": 2101, "screen_name": "MinimaGreen", "notifications": null, "url": null, "created_at": "Mon Aug 15 19:18:15 +0000 2011", "contributors_enabled": false, "time_zone": "Europe/Istanbul", "protected": false, "default_profile": false, "is_translator": false}, "geo": {"type": "Point", "coordinates": [40.7414688, -74.00331557]}, "in_reply_to_user_id_str": null, "possibly_sensitive": false, "lang": "en", "created_at": "Mon Nov 17 19:02:23 +0000 2014", "in_reply_to_status_id_str": null, "place": {"country_code": "US", "url": "https://api.twitter.com/1.1/geo/id/01a9a39529b27f36.json", "country": "United States", "place_type": "city", "bounding_box": {"type": "Polygon", "coordinates": [[[-74.026675, 40.683935], [-73.910408, 40.683935], [-73.910408, 40.877483], [-74.026675, 40.877483]]]}, "contained_within": [], "full_name": "Manhattan, NY", "attributes": {}, "id": "01a9a39529b27f36", "name": "Manhattan"}, "metadata": {"iso_language_code": "en", "result_type": "recent"}}, "data_point": "none", "user_location": "Izmir Ankara Madrid Dublin", "lon": 40.7414688, "content": "I'm at @Google New York in New York, NY https://t.co/27poYMlX27", "tweet_id": 534421307681951744, "user": 355701353, "time": "Mon Nov 17 19:02:23 +0000 2014", "lat": -74.00331557}, "534421171757133824": {"raw_source": {"contributors": null, "truncated": false, "text": "shoutout to ALWAYS going over my fucking data because of the shitty wifi at my dorm", "in_reply_to_status_id": null, "id": 534421171757133824, "favorite_count": 0, "source": "<a href=\"http://twitter.com/download/iphone\" rel=\"nofollow\">Twitter for iPhone</a>", "retweeted": false, "coordinates": {"type": "Point", "coordinates": [-73.96478221, 40.76802834]}, "entities": {"symbols": [], "user_mentions": [], "hashtags": [], "urls": []}, "in_reply_to_screen_name": null, "in_reply_to_user_id": null, "retweet_count": 0, "id_str": "534421171757133824", "favorited": false, "user": {"follow_request_sent": null, "profile_use_background_image": true, "profile_text_color": "333333", "default_profile_image": false, "id": 21681689, "profile_background_image_url_https": "https://pbs.twimg.com/profile_background_images/378800000162171588/UmZPgBHz.jpeg", "verified": false, "profile_location": null, "profile_image_url_https": "https://pbs.twimg.com/profile_images/532712482935427073/pDgt2pYI_normal.jpeg", "profile_sidebar_fill_color": "F6F6F6", "entities": {"url": {"urls": [{"url": "http://t.co/y4DErcdbGu", "indices": [0, 22], "expanded_url": "http://jamierothenberg.tumblr.com", "display_url": "jamierothenberg.tumblr.com"}]}, "description": {"urls": []}}, "followers_count": 834, "profile_sidebar_border_color": "000000", "id_str": "21681689", "profile_background_color": "ACDED6", "listed_count": 2, "is_translation_enabled": false, "utc_offset": -18000, "statuses_count": 25100, "description": "MESSY HAIR", "friends_count": 198, "location": "NYC//", "profile_link_color": "89C9FA", "profile_image_url": "http://pbs.twimg.com/profile_images/532712482935427073/pDgt2pYI_normal.jpeg", "following": null, "geo_enabled": true, "profile_banner_url": "https://pbs.twimg.com/profile_banners/21681689/1410309982", "profile_background_image_url": "http://pbs.twimg.com/profile_background_images/378800000162171588/UmZPgBHz.jpeg", "name": "jamie", "lang": "en", "profile_background_tile": true, "favourites_count": 42989, "screen_name": "yungjimjam", "notifications": null, "url": "http://t.co/y4DErcdbGu", "created_at": "Mon Feb 23 19:11:41 +0000 2009", "contributors_enabled": false, "time_zone": "Quito", "protected": false, "default_profile": false, "is_translator": false}, "geo": {"type": "Point", "coordinates": [40.76802834, -73.96478221]}, "in_reply_to_user_id_str": null, "lang": "en", "created_at": "Mon Nov 17 19:01:51 +0000 2014", "in_reply_to_status_id_str": null, "place": {"country_code": "US", "url": "https://api.twitter.com/1.1/geo/id/01a9a39529b27f36.json", "country": "United States", "place_type": "city", "bounding_box": {"type": "Polygon", "coordinates": [[[-74.026675, 40.683935], [-73.910408, 40.683935], [-73.910408, 40.877483], [-74.026675, 40.877483]]]}, "contained_within": [], "full_name": "Manhattan, NY", "attributes": {}, "id": "01a9a39529b27f36", "name": "Manhattan"}, "metadata": {"iso_language_code": "en", "result_type": "recent"}}, "data_point": "none", "user_location": "NYC//", "lon": 40.76802834, "content": "shoutout to ALWAYS going over my fucking data because of the shitty wifi at my dorm", "tweet_id": 534421171757133824, "user": 21681689, "time": "Mon Nov 17 19:01:51 +0000 2014", "lat": -73.96478221}, "534420787521155072": {"raw_source": {"contributors": null, "truncated": false, "text": "Synergy creates the superlative!studio session with the talented @anthonyflammia (photo:\u2026 http://t.co/SlMfcZlLnX", "in_reply_to_status_id": null, "id": 534420787521155072, "favorite_count": 0, "source": "<a href=\"http://instagram.com\" rel=\"nofollow\">Instagram</a>", "retweeted": false, "coordinates": {"type": "Point", "coordinates": [-73.94689908, 40.80388893]}, "entities": {"symbols": [], "user_mentions": [{"id": 267396296, "indices": [65, 80], "id_str": "267396296", "screen_name": "AnthonyFlammia", "name": "FLAMM"}], "hashtags": [], "urls": [{"url": "http://t.co/SlMfcZlLnX", "indices": [90, 112], "expanded_url": "http://instagram.com/p/vgwTTrMxp9/", "display_url": "instagram.com/p/vgwTTrMxp9/"}]}, "in_reply_to_screen_name": null, "in_reply_to_user_id": null, "retweet_count": 0, "id_str": "534420787521155072", "favorited": false, "user": {"follow_request_sent": null, "profile_use_background_image": false, "profile_text_color": "000000", "default_profile_image": false, "id": 2436464287, "profile_background_image_url_https": "https://abs.twimg.com/images/themes/theme19/bg.gif", "verified": false, "profile_location": null, "profile_image_url_https": "https://pbs.twimg.com/profile_images/454334769136795648/G7FoNgfJ_normal.jpeg", "profile_sidebar_fill_color": "000000", "entities": {"url": {"urls": [{"url": "http://t.co/efv7t6Gydk", "indices": [0, 22], "expanded_url": "http://www.bbthomaz.com", "display_url": "bbthomaz.com"}]}, "description": {"urls": []}}, "followers_count": 181, "profile_sidebar_border_color": "000000", "id_str": "2436464287", "profile_background_color": "000000", "listed_count": 1, "is_translation_enabled": false, "utc_offset": 3600, "statuses_count": 215, "description": "Recording Artist, Songwriter, Composer, Producer. Speak from your soul, paint your emotions, whisper a melody - that's where you find music - BB Thomaz.", "friends_count": 194, "location": "NYC", "profile_link_color": "9266CC", "profile_image_url": "http://pbs.twimg.com/profile_images/454334769136795648/G7FoNgfJ_normal.jpeg", "following": null, "geo_enabled": true, "profile_banner_url": "https://pbs.twimg.com/profile_banners/2436464287/1397158359", "profile_background_image_url": "http://abs.twimg.com/images/themes/theme19/bg.gif", "name": "BBThomaz", "lang": "de", "profile_background_tile": false, "favourites_count": 23, "screen_name": "BBThomazz", "notifications": null, "url": "http://t.co/efv7t6Gydk", "created_at": "Thu Apr 10 03:57:35 +0000 2014", "contributors_enabled": false, "time_zone": "Ljubljana", "protected": false, "default_profile": false, "is_translator": false}, "geo": {"type": "Point", "coordinates": [40.80388893, -73.94689908]}, "in_reply_to_user_id_str": null, "possibly_sensitive": false, "lang": "en", "created_at": "Mon Nov 17 19:00:19 +0000 2014", "in_reply_to_status_id_str": null, "place": {"country_code": "US", "url": "https://api.twitter.com/1.1/geo/id/01a9a39529b27f36.json", "country": "United States", "place_type": "city", "bounding_box": {"type": "Polygon", "coordinates": [[[-74.026675, 40.683935], [-73.910408, 40.683935], [-73.910408, 40.877483], [-74.026675, 40.877483]]]}, "contained_within": [], "full_name": "Manhattan, NY", "attributes": {}, "id": "01a9a39529b27f36", "name": "Manhattan"}, "metadata": {"iso_language_code": "en", "result_type": "recent"}}, "data_point": "none", "user_location": "NYC", "lon": 40.80388893, "content": "Synergy creates the superlative!studio session with the talented @anthonyflammia (photo:\u2026 http://t.co/SlMfcZlLnX", "tweet_id": 534420787521155072, "user": 2436464287, "time": "Mon Nov 17 19:00:19 +0000 2014", "lat": -73.94689908}, "534420789505040384": {"raw_source": {"contributors": null, "truncated": false, "text": "@itsDelaneSean I'm not #oomf lmfaoo!", "in_reply_to_status_id": 534420518313922560, "id": 534420789505040384, "favorite_count": 0, "source": "<a href=\"http://twitter.com/download/iphone\" rel=\"nofollow\">Twitter for iPhone</a>", "retweeted": false, "coordinates": {"type": "Point", "coordinates": [-74.06303007, 40.73037632]}, "entities": {"symbols": [], "user_mentions": [{"id": 328851914, "indices": [0, 14], "id_str": "328851914", "screen_name": "itsDelaneSean", "name": "LANE"}], "hashtags": [{"indices": [23, 28], "text": "oomf"}], "urls": []}, "in_reply_to_screen_name": "itsDelaneSean", "in_reply_to_user_id": 328851914, "retweet_count": 0, "id_str": "534420789505040384", "favorited": false, "user": {"follow_request_sent": null, "profile_use_background_image": true, "profile_text_color": "333333", "default_profile_image": false, "id": 489660028, "profile_background_image_url_https": "https://abs.twimg.com/images/themes/theme14/bg.gif", "verified": false, "profile_location": null, "profile_image_url_https": "https://pbs.twimg.com/profile_images/531689213931315200/qNJq2pk2_normal.jpeg", "profile_sidebar_fill_color": "EFEFEF", "entities": {"description": {"urls": []}}, "followers_count": 579, "profile_sidebar_border_color": "EEEEEE", "id_str": "489660028", "profile_background_color": "131516", "listed_count": 0, "is_translation_enabled": false, "utc_offset": -18000, "statuses_count": 10200, "description": "\u2022sicker than your average\u2022           Instaaaaa:@_hannan", "friends_count": 451, "location": "", "profile_link_color": "009999", "profile_image_url": "http://pbs.twimg.com/profile_images/531689213931315200/qNJq2pk2_normal.jpeg", "following": null, "geo_enabled": true, "profile_banner_url": "https://pbs.twimg.com/profile_banners/489660028/1414073519", "profile_background_image_url": "http://abs.twimg.com/images/themes/theme14/bg.gif", "name": "Haannn", "lang": "en", "profile_background_tile": true, "favourites_count": 1428, "screen_name": "hannanelzoghabi", "notifications": null, "url": null, "created_at": "Sat Feb 11 19:12:18 +0000 2012", "contributors_enabled": false, "time_zone": "Eastern Time (US & Canada)", "protected": false, "default_profile": false, "is_translator": false}, "geo": {"type": "Point", "coordinates": [40.73037632, -74.06303007]}, "in_reply_to_user_id_str": "328851914", "lang": "en", "created_at": "Mon Nov 17 19:00:19 +0000 2014", "in_reply_to_status_id_str": "534420518313922560", "place": {"country_code": "US", "url": "https://api.twitter.com/1.1/geo/id/b046074b1030a44d.json", "country": "United States", "place_type": "city", "bounding_box": {"type": "Polygon", "coordinates": [[[-74.107995, 40.666879], [-74.0253309, 40.666879], [-74.0253309, 40.769124], [-74.107995, 40.769124]]]}, "contained_within": [], "full_name": "Jersey City, NJ", "attributes": {}, "id": "b046074b1030a44d", "name": "Jersey City"}, "metadata": {"iso_language_code": "en", "result_type": "recent"}}, "data_point": "none", "user_location": "", "lon": 40.73037632, "content": "@itsDelaneSean I'm not #oomf lmfaoo!", "tweet_id": 534420789505040384, "user": 489660028, "time": "Mon Nov 17 19:00:19 +0000 2014", "lat": -74.06303007}, "534420787697295361": {"raw_source": {"contributors": null, "truncated": false, "text": "Witnessing a jack'd meeting on the M60 bus.  one of the guys look like Joseline and the other one look like a busted dru hill", "in_reply_to_status_id": null, "id": 534420787697295361, "favorite_count": 0, "source": "<a href=\"http://twitter.com/download/iphone\" rel=\"nofollow\">Twitter for iPhone</a>", "retweeted": false, "coordinates": {"type": "Point", "coordinates": [-73.93825768, 40.80460466]}, "entities": {"symbols": [], "user_mentions": [], "hashtags": [], "urls": []}, "in_reply_to_screen_name": null, "in_reply_to_user_id": null, "retweet_count": 0, "id_str": "534420787697295361", "favorited": false, "user": {"follow_request_sent": null, "profile_use_background_image": true, "profile_text_color": "333333", "default_profile_image": false, "id": 54801127, "profile_background_image_url_https": "https://pbs.twimg.com/profile_background_images/438785719675265025/thhevRg1.png", "verified": false, "profile_location": null, "profile_image_url_https": "https://pbs.twimg.com/profile_images/527947162764976129/J4AwSR0F_normal.jpeg", "profile_sidebar_fill_color": "A0C5C7", "entities": {"url": {"urls": [{"url": "http://t.co/BGJQwl57Ej", "indices": [0, 22], "expanded_url": "http://dvntecvrtis.tumblr.com", "display_url": "dvntecvrtis.tumblr.com"}]}, "description": {"urls": []}}, "followers_count": 1465, "profile_sidebar_border_color": "000000", "id_str": "54801127", "profile_background_color": "030303", "listed_count": 20, "is_translation_enabled": false, "utc_offset": -18000, "statuses_count": 61946, "description": "Morehouse Man. I live-tweet my favorite shows. I'm just trying to wake up to my dreams. My faves tweet me. B Phi 2k11", "friends_count": 786, "location": "New York", "profile_link_color": "00FF00", "profile_image_url": "http://pbs.twimg.com/profile_images/527947162764976129/J4AwSR0F_normal.jpeg", "following": null, "geo_enabled": true, "profile_banner_url": "https://pbs.twimg.com/profile_banners/54801127/1395904078", "profile_background_image_url": "http://pbs.twimg.com/profile_background_images/438785719675265025/thhevRg1.png", "name": " dant\u00e8 curtis ", "lang": "en", "profile_background_tile": true, "favourites_count": 1266, "screen_name": "whayanameis", "notifications": null, "url": "http://t.co/BGJQwl57Ej", "created_at": "Wed Jul 08 04:44:18 +0000 2009", "contributors_enabled": false, "time_zone": "Eastern Time (US & Canada)", "protected": false, "default_profile": false, "is_translator": false}, "geo": {"type": "Point", "coordinates": [40.80460466, -73.93825768]}, "in_reply_to_user_id_str": null, "lang": "en", "created_at": "Mon Nov 17 19:00:19 +0000 2014", "in_reply_to_status_id_str": null, "place": {"country_code": "US", "url": "https://api.twitter.com/1.1/geo/id/01a9a39529b27f36.json", "country": "United States", "place_type": "city", "bounding_box": {"type": "Polygon", "coordinates": [[[-74.026675, 40.683935], [-73.910408, 40.683935], [-73.910408, 40.877483], [-74.026675, 40.877483]]]}, "contained_within": [], "full_name": "Manhattan, NY", "attributes": {}, "id": "01a9a39529b27f36", "name": "Manhattan"}, "metadata": {"iso_language_code": "en", "result_type": "recent"}}, "data_point": "none", "user_location": "New York", "lon": 40.80460466, "content": "Witnessing a jack'd meeting on the M60 bus.  one of the guys look like Joseline and the other one look like a busted dru hill", "tweet_id": 534420787697295361, "user": 54801127, "time": "Mon Nov 17 19:00:19 +0000 2014", "lat": -73.93825768}, "534421427236392960": {"raw_source": {"contributors": null, "truncated": false, "text": "@lutman_sarah We're doing NSF-funded research on why people follow @FieldMuseum. We'd love to talk to you! http://t.co/kdo1TiuzqF", "in_reply_to_status_id": null, "id": 534421427236392960, "favorite_count": 0, "source": "<a href=\"http://twitter.com\" rel=\"nofollow\">Twitter Web Client</a>", "retweeted": false, "coordinates": {"type": "Point", "coordinates": [0.0, 0.0]}, "entities": {"symbols": [], "user_mentions": [{"id": 464981283, "indices": [0, 13], "id_str": "464981283", "screen_name": "lutman_sarah", "name": "Sarah Lutman"}, {"id": 14315537, "indices": [67, 79], "id_str": "14315537", "screen_name": "FieldMuseum", "name": "Field Museum"}], "hashtags": [], "urls": [], "media": [{"expanded_url": "http://twitter.com/twisle/status/534421427236392960/photo/1", "display_url": "pic.twitter.com/kdo1TiuzqF", "url": "http://t.co/kdo1TiuzqF", "media_url_https": "https://pbs.twimg.com/media/B2qldKdCIAAhalD.png", "id_str": "534421426237743104", "sizes": {"small": {"h": 263, "resize": "fit", "w": 340}, "large": {"h": 793, "resize": "fit", "w": 1024}, "medium": {"h": 464, "resize": "fit", "w": 600}, "thumb": {"h": 150, "resize": "crop", "w": 150}}, "indices": [107, 129], "type": "photo", "id": 534421426237743104, "media_url": "http://pbs.twimg.com/media/B2qldKdCIAAhalD.png"}]}, "in_reply_to_screen_name": "lutman_sarah", "in_reply_to_user_id": 464981283, "retweet_count": 0, "id_str": "534421427236392960", "favorited": false, "user": {"follow_request_sent": null, "profile_use_background_image": true, "profile_text_color": "333333", "default_profile_image": false, "id": 2844679045, "profile_background_image_url_https": "https://abs.twimg.com/images/themes/theme1/bg.png", "verified": false, "profile_location": null, "profile_image_url_https": "https://pbs.twimg.com/profile_images/519592870664105984/mQx1GX8o_normal.jpeg", "profile_sidebar_fill_color": "DDEEF6", "entities": {"url": {"urls": [{"url": "http://t.co/CBsRA23HC9", "indices": [0, 22], "expanded_url": "http://cct.edc.org/projects/twisle", "display_url": "cct.edc.org/projects/twisle"}]}, "description": {"urls": []}}, "followers_count": 25, "profile_sidebar_border_color": "FFFFFF", "id_str": "2844679045", "profile_background_color": "ABB8C2", "listed_count": 0, "is_translation_enabled": false, "utc_offset": null, "statuses_count": 140, "description": "TwISLE = Twitter and Informal Science Learning and Engagement: NSF-funded project exploring how people use social media for public science discussions.", "friends_count": 166, "location": "New York, NY", "profile_link_color": "0084B4", "profile_image_url": "http://pbs.twimg.com/profile_images/519592870664105984/mQx1GX8o_normal.jpeg", "following": null, "geo_enabled": true, "profile_background_image_url": "http://abs.twimg.com/images/themes/theme1/bg.png", "name": "TwISLE_CCT", "lang": "en", "profile_background_tile": false, "favourites_count": 2, "screen_name": "twisle", "notifications": null, "url": "http://t.co/CBsRA23HC9", "created_at": "Tue Oct 07 20:25:46 +0000 2014", "contributors_enabled": false, "time_zone": null, "protected": false, "default_profile": false, "is_translator": false}, "geo": {"type": "Point", "coordinates": [0.0, 0.0]}, "in_reply_to_user_id_str": "464981283", "possibly_sensitive": false, "lang": "en", "created_at": "Mon Nov 17 19:02:51 +0000 2014", "in_reply_to_status_id_str": null, "place": {"country_code": "US", "url": "https://api.twitter.com/1.1/geo/id/01a9a39529b27f36.json", "country": "United States", "place_type": "city", "bounding_box": {"type": "Polygon", "coordinates": [[[-74.026675, 40.683935], [-73.910408, 40.683935], [-73.910408, 40.877483], [-74.026675, 40.877483]]]}, "contained_within": [], "full_name": "Manhattan, NY", "attributes": {}, "id": "01a9a39529b27f36", "name": "Manhattan"}, "metadata": {"iso_language_code": "en", "result_type": "recent"}}, "data_point": "none", "user_location": "New York, NY", "lon": 0.0, "content": "@lutman_sarah We're doing NSF-funded research on why people follow @FieldMuseum. We'd love to talk to you! http://t.co/kdo1TiuzqF", "tweet_id": 534421427236392960, "user": 2844679045, "time": "Mon Nov 17 19:02:51 +0000 2014", "lat": 0.0}, "534420643123433472": {"raw_source": {"contributors": null, "truncated": false, "text": "@CreativeNiche We build apps remotely! Our Portfolio \u261ehttp://t.co/yoNfd3pMVl let\u2019s talk :) Email to \u261e info@openwavecomp.com \u260e (212) 209 1537", "in_reply_to_status_id": 533219069282250752, "id": 534420643123433472, "favorite_count": 0, "source": "<a href=\"http://twitter.com\" rel=\"nofollow\">Twitter Web Client</a>", "retweeted": false, "coordinates": {"type": "Point", "coordinates": [0.0, 0.0]}, "entities": {"symbols": [], "user_mentions": [{"id": 23765109, "indices": [0, 14], "id_str": "23765109", "screen_name": "CreativeNiche", "name": "Creative Niche"}], "hashtags": [], "urls": [{"url": "http://t.co/yoNfd3pMVl", "indices": [54, 76], "expanded_url": "http://x.co/5l22M", "display_url": "x.co/5l22M"}]}, "in_reply_to_screen_name": "CreativeNiche", "in_reply_to_user_id": 23765109, "retweet_count": 0, "id_str": "534420643123433472", "favorited": false, "user": {"follow_request_sent": null, "profile_use_background_image": true, "profile_text_color": "333333", "default_profile_image": false, "id": 278011163, "profile_background_image_url_https": "https://pbs.twimg.com/profile_background_images/852037659/f704cc4764beaf45fd255beda3fc77b5.jpeg", "verified": false, "profile_location": null, "profile_image_url_https": "https://pbs.twimg.com/profile_images/1301932832/Openwave_normal.jpg", "profile_sidebar_fill_color": "DDEEF6", "entities": {"url": {"urls": [{"url": "http://t.co/hJz5PkKEvo", "indices": [0, 22], "expanded_url": "http://about.me/App_Developers_New_York", "display_url": "about.me/App_Developers\u2026"}]}, "description": {"urls": []}}, "followers_count": 648, "profile_sidebar_border_color": "FFFFFF", "id_str": "278011163", "profile_background_color": "C0DEED", "listed_count": 9, "is_translation_enabled": false, "utc_offset": -18000, "statuses_count": 3470, "description": "Openwave Computing LLC, NYC an ISO 9001: 2008 certified mobile app Development Company who are on demand now!! We make all sorts of apps for varied platforms!", "friends_count": 1586, "location": "New York", "profile_link_color": "0084B4", "profile_image_url": "http://pbs.twimg.com/profile_images/1301932832/Openwave_normal.jpg", "following": null, "geo_enabled": true, "profile_banner_url": "https://pbs.twimg.com/profile_banners/278011163/1398260309", "profile_background_image_url": "http://pbs.twimg.com/profile_background_images/852037659/f704cc4764beaf45fd255beda3fc77b5.jpeg", "name": "Apps Development NYC", "lang": "en", "profile_background_tile": false, "favourites_count": 171, "screen_name": "OWCServices", "notifications": null, "url": "http://t.co/hJz5PkKEvo", "created_at": "Wed Apr 06 12:38:17 +0000 2011", "contributors_enabled": false, "time_zone": "Eastern Time (US & Canada)", "protected": false, "default_profile": false, "is_translator": false}, "geo": {"type": "Point", "coordinates": [0.0, 0.0]}, "in_reply_to_user_id_str": "23765109", "possibly_sensitive": false, "lang": "en", "created_at": "Mon Nov 17 18:59:45 +0000 2014", "in_reply_to_status_id_str": "533219069282250752", "place": {"country_code": "US", "url": "https://api.twitter.com/1.1/geo/id/94965b2c45386f87.json", "country": "United States", "place_type": "admin", "bounding_box": {"type": "Polygon", "coordinates": [[[-79.76259, 40.477383], [-71.777492, 40.477383], [-71.777492, 45.015851], [-79.76259, 45.015851]]]}, "contained_within": [], "full_name": "New York, US", "attributes": {}, "id": "94965b2c45386f87", "name": "New York"}, "metadata": {"iso_language_code": "en", "result_type": "recent"}}, "data_point": "none", "user_location": "New York", "lon": 0.0, "content": "@CreativeNiche We build apps remotely! Our Portfolio \u261ehttp://t.co/yoNfd3pMVl let\u2019s talk :) Email to \u261e info@openwavecomp.com \u260e (212) 209 1537", "tweet_id": 534420643123433472, "user": 278011163, "time": "Mon Nov 17 18:59:45 +0000 2014", "lat": 0.0}, "534421431837536257": {"raw_source": {"contributors": null, "truncated": false, "text": "Had a short conversation with an older man at the deli, when I go to pay I learn he paid for my whole order. Brightened up this rainy day \ud83d\ude0f", "in_reply_to_status_id": null, "id": 534421431837536257, "favorite_count": 0, "source": "<a href=\"http://twitter.com/download/iphone\" rel=\"nofollow\">Twitter for iPhone</a>", "retweeted": false, "coordinates": {"type": "Point", "coordinates": [-73.94321188, 40.61053083]}, "entities": {"symbols": [], "user_mentions": [], "hashtags": [], "urls": []}, "in_reply_to_screen_name": null, "in_reply_to_user_id": null, "retweet_count": 0, "id_str": "534421431837536257", "favorited": false, "user": {"follow_request_sent": null, "profile_use_background_image": true, "profile_text_color": "47484D", "default_profile_image": false, "id": 371943293, "profile_background_image_url_https": "https://pbs.twimg.com/profile_background_images/333678365/xf009659dd2d3b8568301dab4b6df559.png", "verified": false, "profile_location": null, "profile_image_url_https": "https://pbs.twimg.com/profile_images/529470018875305984/kVomIl3__normal.jpeg", "profile_sidebar_fill_color": "BABAB2", "entities": {"description": {"urls": []}}, "followers_count": 312, "profile_sidebar_border_color": "BABAB2", "id_str": "371943293", "profile_background_color": "FFFFFF", "listed_count": 2, "is_translation_enabled": false, "utc_offset": -18000, "statuses_count": 9604, "description": "", "friends_count": 630, "location": "", "profile_link_color": "2891E2", "profile_image_url": "http://pbs.twimg.com/profile_images/529470018875305984/kVomIl3__normal.jpeg", "following": null, "geo_enabled": true, "profile_banner_url": "https://pbs.twimg.com/profile_banners/371943293/1378763886", "profile_background_image_url": "http://pbs.twimg.com/profile_background_images/333678365/xf009659dd2d3b8568301dab4b6df559.png", "name": "D00T", "lang": "en", "profile_background_tile": true, "favourites_count": 4031, "screen_name": "nooorraaaaa", "notifications": null, "url": null, "created_at": "Sun Sep 11 20:26:29 +0000 2011", "contributors_enabled": false, "time_zone": "Eastern Time (US & Canada)", "protected": false, "default_profile": false, "is_translator": false}, "geo": {"type": "Point", "coordinates": [40.61053083, -73.94321188]}, "in_reply_to_user_id_str": null, "lang": "en", "created_at": "Mon Nov 17 19:02:53 +0000 2014", "in_reply_to_status_id_str": null, "place": {"country_code": "US", "url": "https://api.twitter.com/1.1/geo/id/011add077f4d2da3.json", "country": "United States", "place_type": "city", "bounding_box": {"type": "Polygon", "coordinates": [[[-74.041878, 40.570842], [-73.855673, 40.570842], [-73.855673, 40.739434], [-74.041878, 40.739434]]]}, "contained_within": [], "full_name": "Brooklyn, NY", "attributes": {}, "id": "011add077f4d2da3", "name": "Brooklyn"}, "metadata": {"iso_language_code": "en", "result_type": "recent"}}, "data_point": "none", "user_location": "", "lon": 40.61053083, "content": "Had a short conversation with an older man at the deli, when I go to pay I learn he paid for my whole order. Brightened up this rainy day \ud83d\ude0f", "tweet_id": 534421431837536257, "user": 371943293, "time": "Mon Nov 17 19:02:53 +0000 2014", "lat": -73.94321188}, "534421436870688769": {"raw_source": {"contributors": null, "truncated": false, "text": "#itsfechi I love you lol", "in_reply_to_status_id": null, "id": 534421436870688769, "favorite_count": 0, "source": "<a href=\"http://twitter.com\" rel=\"nofollow\">Twitter Web Client</a>", "retweeted": false, "coordinates": {"type": "Point", "coordinates": [0.0, 0.0]}, "entities": {"symbols": [], "user_mentions": [], "hashtags": [{"indices": [0, 9], "text": "itsfechi"}], "urls": []}, "in_reply_to_screen_name": null, "in_reply_to_user_id": null, "retweet_count": 0, "id_str": "534421436870688769", "favorited": false, "user": {"follow_request_sent": null, "profile_use_background_image": true, "profile_text_color": "333333", "default_profile_image": false, "id": 2257247228, "profile_background_image_url_https": "https://abs.twimg.com/images/themes/theme16/bg.gif", "verified": false, "profile_location": null, "profile_image_url_https": "https://pbs.twimg.com/profile_images/504085289464127490/R_WG-UAw_normal.jpeg", "profile_sidebar_fill_color": "DDFFCC", "entities": {"description": {"urls": []}}, "followers_count": 696, "profile_sidebar_border_color": "FFFFFF", "id_str": "2257247228", "profile_background_color": "9AE4E8", "listed_count": 4, "is_translation_enabled": false, "utc_offset": -18000, "statuses_count": 13015, "description": "laughing enthusiast, animal lover, skilled ugly face maker.. avid blurter outer, fun liker , verbal abuser of animal abusers, skilled in kicky dance & freshness", "friends_count": 936, "location": "NYC", "profile_link_color": "0084B4", "profile_image_url": "http://pbs.twimg.com/profile_images/504085289464127490/R_WG-UAw_normal.jpeg", "following": null, "geo_enabled": true, "profile_banner_url": "https://pbs.twimg.com/profile_banners/2257247228/1408048535", "profile_background_image_url": "http://abs.twimg.com/images/themes/theme16/bg.gif", "name": "KimK'sFirstNose", "lang": "en", "profile_background_tile": false, "favourites_count": 7612, "screen_name": "ClaireBaenes", "notifications": null, "url": null, "created_at": "Sun Dec 22 04:06:04 +0000 2013", "contributors_enabled": false, "time_zone": "Eastern Time (US & Canada)", "protected": false, "default_profile": false, "is_translator": false}, "geo": {"type": "Point", "coordinates": [0.0, 0.0]}, "in_reply_to_user_id_str": null, "lang": "en", "created_at": "Mon Nov 17 19:02:54 +0000 2014", "in_reply_to_status_id_str": null, "place": {"country_code": "US", "url": "https://api.twitter.com/1.1/geo/id/002e24c6736f069d.json", "country": "United States", "place_type": "city", "bounding_box": {"type": "Polygon", "coordinates": [[[-73.933612, 40.785365], [-73.765271, 40.785365], [-73.765271, 40.91533], [-73.933612, 40.91533]]]}, "contained_within": [], "full_name": "Bronx, NY", "attributes": {}, "id": "002e24c6736f069d", "name": "Bronx"}, "metadata": {"iso_language_code": "en", "result_type": "recent"}}, "data_point": "none", "user_location": "NYC", "lon": 0.0, "content": "#itsfechi I love you lol", "tweet_id": 534421436870688769, "user": 2257247228, "time": "Mon Nov 17 19:02:54 +0000 2014", "lat": 0.0}, "534421175804637184": {"raw_source": {"contributors": null, "truncated": false, "text": "@kaaacey_ @Juanchoo_27 lmaoo staaaap Juan does fine by himself.", "in_reply_to_status_id": 534420764968382465, "id": 534421175804637184, "favorite_count": 0, "source": "<a href=\"http://twitter.com/download/android\" rel=\"nofollow\">Twitter for Android</a>", "retweeted": false, "coordinates": {"type": "Point", "coordinates": [-73.8609674, 40.7375594]}, "entities": {"symbols": [], "user_mentions": [{"id": 2268098459, "indices": [0, 9], "id_str": "2268098459", "screen_name": "kaaacey_", "name": "Kate"}, {"id": 1450153940, "indices": [10, 22], "id_str": "1450153940", "screen_name": "Juanchoo_27", "name": "Juan Camilo Henao"}], "hashtags": [], "urls": []}, "in_reply_to_screen_name": "kaaacey_", "in_reply_to_user_id": 2268098459, "retweet_count": 0, "id_str": "534421175804637184", "favorited": false, "user": {"follow_request_sent": null, "profile_use_background_image": true, "profile_text_color": "333333", "default_profile_image": false, "id": 244642108, "profile_background_image_url_https": "https://pbs.twimg.com/profile_background_images/378800000085745489/f656d9cdfc2cae37c807b2caec0d1809.jpeg", "verified": false, "profile_location": null, "profile_image_url_https": "https://pbs.twimg.com/profile_images/520208176512516096/yhXs6Ujd_normal.jpeg", "profile_sidebar_fill_color": "EFEFEF", "entities": {"url": {"urls": [{"url": "http://t.co/OoMsneqODn", "indices": [0, 22], "expanded_url": "http://andrevstheworld.tumblr.com/", "display_url": "andrevstheworld.tumblr.com"}]}, "description": {"urls": []}}, "followers_count": 432, "profile_sidebar_border_color": "FFFFFF", "id_str": "244642108", "profile_background_color": "1F1E1F", "listed_count": 1, "is_translation_enabled": false, "utc_offset": -32400, "statuses_count": 20004, "description": "C'est la vie - Scorpio - Don't waste my time.", "friends_count": 391, "location": "New York City", "profile_link_color": "080808", "profile_image_url": "http://pbs.twimg.com/profile_images/520208176512516096/yhXs6Ujd_normal.jpeg", "following": null, "geo_enabled": true, "profile_banner_url": "https://pbs.twimg.com/profile_banners/244642108/1378880557", "profile_background_image_url": "http://pbs.twimg.com/profile_background_images/378800000085745489/f656d9cdfc2cae37c807b2caec0d1809.jpeg", "name": "CHANDLER", "lang": "en", "profile_background_tile": true, "favourites_count": 11918, "screen_name": "__Chandler", "notifications": null, "url": "http://t.co/OoMsneqODn", "created_at": "Sat Jan 29 19:54:06 +0000 2011", "contributors_enabled": false, "time_zone": "Alaska", "protected": false, "default_profile": false, "is_translator": false}, "geo": {"type": "Point", "coordinates": [40.7375594, -73.8609674]}, "in_reply_to_user_id_str": "2268098459", "lang": "en", "created_at": "Mon Nov 17 19:01:52 +0000 2014", "in_reply_to_status_id_str": "534420764968382465", "place": {"country_code": "US", "url": "https://api.twitter.com/1.1/geo/id/00c39537733fa112.json", "country": "United States", "place_type": "city", "bounding_box": {"type": "Polygon", "coordinates": [[[-73.962582, 40.541722], [-73.699793, 40.541722], [-73.699793, 40.8000371], [-73.962582, 40.8000371]]]}, "contained_within": [], "full_name": "Queens, NY", "attributes": {}, "id": "00c39537733fa112", "name": "Queens"}, "metadata": {"iso_language_code": "en", "result_type": "recent"}}, "data_point": "none", "user_location": "New York City", "lon": 40.7375594, "content": "@kaaacey_ @Juanchoo_27 lmaoo staaaap Juan does fine by himself.", "tweet_id": 534421175804637184, "user": 244642108, "time": "Mon Nov 17 19:01:52 +0000 2014", "lat": -73.8609674}}