{"536107026804666369": {"raw_source": {"contributors": null, "truncated": false, "text": "Hey! I'm on #Kik - my username is 'freezypolo1482' http://t.co/9TZHtcY9DK http://t.co/jbSQKpAxwq", "in_reply_to_status_id": null, "id": 536107026804666369, "favorite_count": 0, "source": "<a href=\"http://twitter.com/download/android\" rel=\"nofollow\">Twitter for Android</a>", "retweeted": false, "coordinates": {"type": "Point", "coordinates": [-73.9646491, 40.6356323]}, "entities": {"symbols": [], "user_mentions": [], "hashtags": [{"indices": [12, 16], "text": "Kik"}], "urls": [{"url": "http://t.co/9TZHtcY9DK", "indices": [51, 73], "expanded_url": "http://kik.me/freezypolo1482", "display_url": "kik.me/freezypolo1482"}], "media": [{"expanded_url": "http://twitter.com/YBFREEZYNHB/status/536107026804666369/photo/1", "display_url": "pic.twitter.com/jbSQKpAxwq", "url": "http://t.co/jbSQKpAxwq", "media_url_https": "https://pbs.twimg.com/media/B3Cif_vCEAA8Ivl.jpg", "id_str": "536107026225434624", "sizes": {"small": {"h": 340, "resize": "fit", "w": 340}, "large": {"h": 640, "resize": "fit", "w": 640}, "medium": {"h": 600, "resize": "fit", "w": 600}, "thumb": {"h": 150, "resize": "crop", "w": 150}}, "indices": [74, 96], "type": "photo", "id": 536107026225434624, "media_url": "http://pbs.twimg.com/media/B3Cif_vCEAA8Ivl.jpg"}]}, "in_reply_to_screen_name": null, "in_reply_to_user_id": null, "retweet_count": 0, "id_str": "536107026804666369", "favorited": false, "user": {"follow_request_sent": null, "profile_use_background_image": true, "profile_text_color": "333333", "default_profile_image": false, "id": 2481503431, "profile_background_image_url_https": "https://abs.twimg.com/images/themes/theme1/bg.png", "verified": false, "profile_location": null, "profile_image_url_https": "https://pbs.twimg.com/profile_images/531609446867542016/WiS2rLfw_normal.jpeg", "profile_sidebar_fill_color": "DDEEF6", "entities": {"description": {"urls": []}}, "followers_count": 45, "profile_sidebar_border_color": "C0DEED", "id_str": "2481503431", "profile_background_color": "C0DEED", "listed_count": 6, "is_translation_enabled": false, "utc_offset": null, "statuses_count": 144, "description": "WXLFPAXKENT A RAP ARTIST EVILMINDTANK FLATBUSH", "friends_count": 308, "location": "", "profile_link_color": "0084B4", "profile_image_url": "http://pbs.twimg.com/profile_images/531609446867542016/WiS2rLfw_normal.jpeg", "following": null, "geo_enabled": true, "profile_banner_url": "https://pbs.twimg.com/profile_banners/2481503431/1415006728", "profile_background_image_url": "http://abs.twimg.com/images/themes/theme1/bg.png", "name": "EVILMINDTANK", "lang": "en", "profile_background_tile": false, "favourites_count": 18, "screen_name": "YBFREEZYNHB", "notifications": null, "url": null, "created_at": "Wed May 07 06:01:19 +0000 2014", "contributors_enabled": false, "time_zone": null, "protected": false, "default_profile": true, "is_translator": false}, "geo": {"type": "Point", "coordinates": [40.6356323, -73.9646491]}, "in_reply_to_user_id_str": null, "possibly_sensitive": false, "lang": "en", "created_at": "Sat Nov 22 10:40:50 +0000 2014", "in_reply_to_status_id_str": null, "place": {"country_code": "US", "url": "https://api.twitter.com/1.1/geo/id/011add077f4d2da3.json", "country": "United States", "place_type": "city", "bounding_box": {"type": "Polygon", "coordinates": [[[-74.041878, 40.570842], [-73.855673, 40.570842], [-73.855673, 40.739434], [-74.041878, 40.739434]]]}, "contained_within": [], "full_name": "Brooklyn, NY", "attributes": {}, "id": "011add077f4d2da3", "name": "Brooklyn"}, "metadata": {"iso_language_code": "en", "result_type": "recent"}}, "data_point": "none", "user_location": "", "lon": 40.6356323, "content": "Hey! I'm on #Kik - my username is 'freezypolo1482' http://t.co/9TZHtcY9DK http://t.co/jbSQKpAxwq", "tweet_id": 536107026804666369, "user": 2481503431, "time": "Sat Nov 22 10:40:50 +0000 2014", "lat": -73.9646491}, "536107051567808512": {"raw_source": {"contributors": null, "truncated": false, "text": "http://t.co/qAht40mFlm", "in_reply_to_status_id": null, "id": 536107051567808512, "favorite_count": 0, "source": "<a href=\"http://twitter.com/download/iphone\" rel=\"nofollow\">Twitter for iPhone</a>", "retweeted": false, "coordinates": {"type": "Point", "coordinates": [-73.98887763, 40.69723577]}, "entities": {"symbols": [], "user_mentions": [], "hashtags": [], "urls": [], "media": [{"expanded_url": "http://twitter.com/yulebowdown/status/536107051567808512/photo/1", "display_url": "pic.twitter.com/qAht40mFlm", "url": "http://t.co/qAht40mFlm", "media_url_https": "https://pbs.twimg.com/media/B3CihOeIMAAy5d6.jpg", "id_str": "536107047360933888", "sizes": {"small": {"h": 255, "resize": "fit", "w": 340}, "large": {"h": 640, "resize": "fit", "w": 852}, "medium": {"h": 450, "resize": "fit", "w": 600}, "thumb": {"h": 150, "resize": "crop", "w": 150}}, "indices": [0, 22], "type": "photo", "id": 536107047360933888, "media_url": "http://pbs.twimg.com/media/B3CihOeIMAAy5d6.jpg"}]}, "in_reply_to_screen_name": null, "in_reply_to_user_id": null, "retweet_count": 0, "id_str": "536107051567808512", "favorited": false, "user": {"follow_request_sent": null, "profile_use_background_image": true, "profile_text_color": "333333", "default_profile_image": false, "id": 1460365867, "profile_background_image_url_https": "https://pbs.twimg.com/profile_background_images/493999626425352193/2P5l0WNF.jpeg", "verified": false, "profile_location": null, "profile_image_url_https": "https://pbs.twimg.com/profile_images/535846362886443008/kpwMaSqb_normal.jpeg", "profile_sidebar_fill_color": "DDEEF6", "entities": {"description": {"urls": []}}, "followers_count": 494, "profile_sidebar_border_color": "000000", "id_str": "1460365867", "profile_background_color": "C0DEED", "listed_count": 9, "is_translation_enabled": false, "utc_offset": -18000, "statuses_count": 18068, "description": "im the blonde one", "friends_count": 217, "location": "crooklyn", "profile_link_color": "0084B4", "profile_image_url": "http://pbs.twimg.com/profile_images/535846362886443008/kpwMaSqb_normal.jpeg", "following": null, "geo_enabled": true, "profile_banner_url": "https://pbs.twimg.com/profile_banners/1460365867/1416652002", "profile_background_image_url": "http://pbs.twimg.com/profile_background_images/493999626425352193/2P5l0WNF.jpeg", "name": "mica", "lang": "en", "profile_background_tile": true, "favourites_count": 10325, "screen_name": "yulebowdown", "notifications": null, "url": null, "created_at": "Sun May 26 18:36:19 +0000 2013", "contributors_enabled": false, "time_zone": "Eastern Time (US & Canada)", "protected": false, "default_profile": false, "is_translator": false}, "geo": {"type": "Point", "coordinates": [40.69723577, -73.98887763]}, "in_reply_to_user_id_str": null, "possibly_sensitive": false, "lang": "und", "created_at": "Sat Nov 22 10:40:56 +0000 2014", "in_reply_to_status_id_str": null, "place": {"country_code": "US", "url": "https://api.twitter.com/1.1/geo/id/011add077f4d2da3.json", "country": "United States", "place_type": "city", "bounding_box": {"type": "Polygon", "coordinates": [[[-74.041878, 40.570842], [-73.855673, 40.570842], [-73.855673, 40.739434], [-74.041878, 40.739434]]]}, "contained_within": [], "full_name": "Brooklyn, NY", "attributes": {}, "id": "011add077f4d2da3", "name": "Brooklyn"}, "metadata": {"iso_language_code": "und", "result_type": "recent"}}, "data_point": "none", "user_location": "crooklyn", "lon": 40.69723577, "content": "http://t.co/qAht40mFlm", "tweet_id": 536107051567808512, "user": 1460365867, "time": "Sat Nov 22 10:40:56 +0000 2014", "lat": -73.98887763}, "536107715626807297": {"raw_source": {"contributors": null, "truncated": false, "text": "djriddlesnyc killed it tonight lastregabk Thank you to everyone who made it out!!! See you all\u2026 http://t.co/7teRfvN86H", "in_reply_to_status_id": null, "id": 536107715626807297, "favorite_count": 0, "source": "<a href=\"http://instagram.com\" rel=\"nofollow\">Instagram</a>", "retweeted": false, "coordinates": {"type": "Point", "coordinates": [-73.961435, 40.606336]}, "entities": {"symbols": [], "user_mentions": [], "hashtags": [], "urls": [{"url": "http://t.co/7teRfvN86H", "indices": [96, 118], "expanded_url": "http://instagram.com/p/vsvbW6DsEz/", "display_url": "instagram.com/p/vsvbW6DsEz/"}]}, "in_reply_to_screen_name": null, "in_reply_to_user_id": null, "retweet_count": 0, "id_str": "536107715626807297", "favorited": false, "user": {"follow_request_sent": null, "profile_use_background_image": true, "profile_text_color": "333333", "default_profile_image": false, "id": 853202928, "profile_background_image_url_https": "https://abs.twimg.com/images/themes/theme1/bg.png", "verified": false, "profile_location": null, "profile_image_url_https": "https://pbs.twimg.com/profile_images/2741998707/aca002dc05ecc2181db1931ec47e9bc1_normal.jpeg", "profile_sidebar_fill_color": "DDEEF6", "entities": {"url": {"urls": [{"url": "http://t.co/F9xzdxb6Ub", "indices": [0, 22], "expanded_url": "http://www.badassacademy.com", "display_url": "badassacademy.com"}]}, "description": {"urls": []}}, "followers_count": 707, "profile_sidebar_border_color": "C0DEED", "id_str": "853202928", "profile_background_color": "C0DEED", "listed_count": 1, "is_translation_enabled": false, "utc_offset": null, "statuses_count": 532, "description": "#SocialMink #BadAssAcademy #RatedSM Work like there is someone working twenty-four hours a day to take it all away from you. ~ Mark Cuban", "friends_count": 1987, "location": "Brooklyn, New York", "profile_link_color": "0084B4", "profile_image_url": "http://pbs.twimg.com/profile_images/2741998707/aca002dc05ecc2181db1931ec47e9bc1_normal.jpeg", "following": null, "geo_enabled": true, "profile_background_image_url": "http://abs.twimg.com/images/themes/theme1/bg.png", "name": "Jerry Balistreri", "lang": "en", "profile_background_tile": false, "favourites_count": 27, "screen_name": "JerryBalistreri", "notifications": null, "url": "http://t.co/F9xzdxb6Ub", "created_at": "Sat Sep 29 16:43:29 +0000 2012", "contributors_enabled": false, "time_zone": null, "protected": false, "default_profile": true, "is_translator": false}, "geo": {"type": "Point", "coordinates": [40.606336, -73.961435]}, "in_reply_to_user_id_str": null, "possibly_sensitive": false, "lang": "en", "created_at": "Sat Nov 22 10:43:34 +0000 2014", "in_reply_to_status_id_str": null, "place": {"country_code": "US", "url": "https://api.twitter.com/1.1/geo/id/011add077f4d2da3.json", "country": "United States", "place_type": "city", "bounding_box": {"type": "Polygon", "coordinates": [[[-74.041878, 40.570842], [-73.855673, 40.570842], [-73.855673, 40.739434], [-74.041878, 40.739434]]]}, "contained_within": [], "full_name": "Brooklyn, NY", "attributes": {}, "id": "011add077f4d2da3", "name": "Brooklyn"}, "metadata": {"iso_language_code": "en", "result_type": "recent"}}, "data_point": "none", "user_location": "Brooklyn, New York", "lon": 40.606336, "content": "djriddlesnyc killed it tonight lastregabk Thank you to everyone who made it out!!! See you all\u2026 http://t.co/7teRfvN86H", "tweet_id": 536107715626807297, "user": 853202928, "time": "Sat Nov 22 10:43:34 +0000 2014", "lat": -73.961435}, "536107515264897024": {"raw_source": {"contributors": null, "truncated": false, "text": "@BetteMidler sings \u2018Too Many Fish In The Sea\u2019 http://t.co/zp698yryM4 via @todayshow", "in_reply_to_status_id": null, "id": 536107515264897024, "favorite_count": 0, "source": "<a href=\"http://twitter.com/download/android\" rel=\"nofollow\">Twitter for Android</a>", "retweeted": false, "coordinates": {"type": "Point", "coordinates": [-73.9427503, 40.8397102]}, "entities": {"symbols": [], "user_mentions": [{"id": 139823781, "indices": [0, 12], "id_str": "139823781", "screen_name": "BetteMidler", "name": "Bette Midler"}, {"id": 7744592, "indices": [73, 83], "id_str": "7744592", "screen_name": "TODAYshow", "name": "TODAY "}], "hashtags": [], "urls": [{"url": "http://t.co/zp698yryM4", "indices": [46, 68], "expanded_url": "http://www.today.com/video/today/56404309", "display_url": "today.com/video/today/56\u2026"}]}, "in_reply_to_screen_name": "BetteMidler", "in_reply_to_user_id": 139823781, "retweet_count": 0, "id_str": "536107515264897024", "favorited": false, "user": {"follow_request_sent": null, "profile_use_background_image": true, "profile_text_color": "F7A18E", "default_profile_image": false, "id": 232375375, "profile_background_image_url_https": "https://pbs.twimg.com/profile_background_images/378800000117259685/6503fbde2c95747381bd8670d6b78ed8.jpeg", "verified": false, "profile_location": null, "profile_image_url_https": "https://pbs.twimg.com/profile_images/378800000083368851/56f3b0a296386fa22832d7757e5ed5a9_normal.jpeg", "profile_sidebar_fill_color": "FFD4B2", "entities": {"url": {"urls": [{"url": "http://t.co/lZe6rO6UvW", "indices": [0, 22], "expanded_url": "http://www.youtube.com/TheLunaShowNY", "display_url": "youtube.com/TheLunaShowNY"}]}, "description": {"urls": []}}, "followers_count": 2965, "profile_sidebar_border_color": "FFFFFF", "id_str": "232375375", "profile_background_color": "0A0909", "listed_count": 53, "is_translation_enabled": false, "utc_offset": -21600, "statuses_count": 36241, "description": "I'm a published & exhibited artist. Host of YouTube's The Luna Show. Work @GMHC. I'm a Mentor, Photographer, Activist, Icon & Ball Walker (Khan). Hall of Famer", "friends_count": 2660, "location": "New York City", "profile_link_color": "0099CC", "profile_image_url": "http://pbs.twimg.com/profile_images/378800000083368851/56f3b0a296386fa22832d7757e5ed5a9_normal.jpeg", "following": null, "geo_enabled": true, "profile_banner_url": "https://pbs.twimg.com/profile_banners/232375375/1398364219", "profile_background_image_url": "http://pbs.twimg.com/profile_background_images/378800000117259685/6503fbde2c95747381bd8670d6b78ed8.jpeg", "name": "Luna Luis ", "lang": "en", "profile_background_tile": true, "favourites_count": 241, "screen_name": "LegendaryLuna", "notifications": null, "url": "http://t.co/lZe6rO6UvW", "created_at": "Fri Dec 31 00:16:33 +0000 2010", "contributors_enabled": false, "time_zone": "Central Time (US & Canada)", "protected": false, "default_profile": false, "is_translator": false}, "geo": {"type": "Point", "coordinates": [40.8397102, -73.9427503]}, "in_reply_to_user_id_str": "139823781", "possibly_sensitive": false, "lang": "en", "created_at": "Sat Nov 22 10:42:46 +0000 2014", "in_reply_to_status_id_str": null, "place": {"country_code": "US", "url": "https://api.twitter.com/1.1/geo/id/01a9a39529b27f36.json", "country": "United States", "place_type": "city", "bounding_box": {"type": "Polygon", "coordinates": [[[-74.026675, 40.683935], [-73.910408, 40.683935], [-73.910408, 40.877483], [-74.026675, 40.877483]]]}, "contained_within": [], "full_name": "Manhattan, NY", "attributes": {}, "id": "01a9a39529b27f36", "name": "Manhattan"}, "metadata": {"iso_language_code": "en", "result_type": "recent"}}, "data_point": "none", "user_location": "New York City", "lon": 40.8397102, "content": "@BetteMidler sings \u2018Too Many Fish In The Sea\u2019 http://t.co/zp698yryM4 via @todayshow", "tweet_id": 536107515264897024, "user": 232375375, "time": "Sat Nov 22 10:42:46 +0000 2014", "lat": -73.9427503}, "536106652085542912": {"raw_source": {"contributors": null, "truncated": false, "text": "Appreciating innovation... (at @Foursquare HQ in New York, NY) https://t.co/i7eNiXDPEs", "in_reply_to_status_id": null, "id": 536106652085542912, "favorite_count": 0, "source": "<a href=\"http://foursquare.com\" rel=\"nofollow\">Foursquare</a>", "retweeted": false, "coordinates": {"type": "Point", "coordinates": [-73.9972651, 40.72412842]}, "entities": {"symbols": [], "user_mentions": [{"id": 14120151, "indices": [31, 42], "id_str": "14120151", "screen_name": "foursquare", "name": "Foursquare"}], "hashtags": [], "urls": [{"url": "https://t.co/i7eNiXDPEs", "indices": [63, 86], "expanded_url": "https://www.swarmapp.com/c/349YTJcBvAR", "display_url": "swarmapp.com/c/349YTJcBvAR"}]}, "in_reply_to_screen_name": null, "in_reply_to_user_id": null, "retweet_count": 0, "id_str": "536106652085542912", "favorited": false, "user": {"follow_request_sent": null, "profile_use_background_image": true, "profile_text_color": "424242", "default_profile_image": false, "id": 31245488, "profile_background_image_url_https": "https://pbs.twimg.com/profile_background_images/446363463971897345/8jx3k0r8.jpeg", "verified": false, "profile_location": null, "profile_image_url_https": "https://pbs.twimg.com/profile_images/378800000307867829/53a316b1ea62574b174b7079bc6cac6c_normal.jpeg", "profile_sidebar_fill_color": "D8FF70", "entities": {"url": {"urls": [{"url": "http://t.co/94a11FBVEu", "indices": [0, 22], "expanded_url": "http://about.me/mikeortega", "display_url": "about.me/mikeortega"}]}, "description": {"urls": []}}, "followers_count": 208, "profile_sidebar_border_color": "FFFFFF", "id_str": "31245488", "profile_background_color": "007AB3", "listed_count": 11, "is_translation_enabled": false, "utc_offset": -21600, "statuses_count": 1988, "description": "NOLA native, Sr UX/Designer at Verizon Wireless, married father of two, love my Labrador retriever. I'm also an Arkansas United soccer coach in my spare time.", "friends_count": 307, "location": "Arkansas, USA", "profile_link_color": "0066CC", "profile_image_url": "http://pbs.twimg.com/profile_images/378800000307867829/53a316b1ea62574b174b7079bc6cac6c_normal.jpeg", "following": null, "geo_enabled": true, "profile_banner_url": "https://pbs.twimg.com/profile_banners/31245488/1399218411", "profile_background_image_url": "http://pbs.twimg.com/profile_background_images/446363463971897345/8jx3k0r8.jpeg", "name": "Mike Ortega", "lang": "en", "profile_background_tile": true, "favourites_count": 96, "screen_name": "PrimeMovr", "notifications": null, "url": "http://t.co/94a11FBVEu", "created_at": "Tue Apr 14 22:18:39 +0000 2009", "contributors_enabled": false, "time_zone": "Central Time (US & Canada)", "protected": false, "default_profile": false, "is_translator": false}, "geo": {"type": "Point", "coordinates": [40.72412842, -73.9972651]}, "in_reply_to_user_id_str": null, "possibly_sensitive": false, "lang": "en", "created_at": "Sat Nov 22 10:39:20 +0000 2014", "in_reply_to_status_id_str": null, "place": {"country_code": "US", "url": "https://api.twitter.com/1.1/geo/id/01a9a39529b27f36.json", "country": "United States", "place_type": "city", "bounding_box": {"type": "Polygon", "coordinates": [[[-74.026675, 40.683935], [-73.910408, 40.683935], [-73.910408, 40.877483], [-74.026675, 40.877483]]]}, "contained_within": [], "full_name": "Manhattan, NY", "attributes": {}, "id": "01a9a39529b27f36", "name": "Manhattan"}, "metadata": {"iso_language_code": "en", "result_type": "recent"}}, "data_point": "none", "user_location": "Arkansas, USA", "lon": 40.72412842, "content": "Appreciating innovation... (at @Foursquare HQ in New York, NY) https://t.co/i7eNiXDPEs", "tweet_id": 536106652085542912, "user": 31245488, "time": "Sat Nov 22 10:39:20 +0000 2014", "lat": -73.9972651}, "536106380709871616": {"raw_source": {"contributors": null, "truncated": false, "text": "@alicegilder @gh0stparties New York is just fascinating, currently clear. This are some guides to check out: http://t.co/rzlYeqKE95", "in_reply_to_status_id": 536106026194706432, "id": 536106380709871616, "favorite_count": 0, "source": "<a href=\"http://shoudio.com\" rel=\"nofollow\">Shoudio</a>", "retweeted": false, "coordinates": {"type": "Point", "coordinates": [-74.0059413, 40.7127837]}, "entities": {"symbols": [], "user_mentions": [{"id": 303491099, "indices": [0, 12], "id_str": "303491099", "screen_name": "alicegilder", "name": "Alice Gilder"}, {"id": 82975510, "indices": [13, 26], "id_str": "82975510", "screen_name": "gh0stparties", "name": "Kate"}], "hashtags": [], "urls": [{"url": "http://t.co/rzlYeqKE95", "indices": [109, 131], "expanded_url": "http://talesandtours.com/travel-audio-guides-in/new-york.html", "display_url": "talesandtours.com/travel-audio-g\u2026"}]}, "in_reply_to_screen_name": "alicegilder", "in_reply_to_user_id": 303491099, "retweet_count": 0, "id_str": "536106380709871616", "favorited": false, "user": {"follow_request_sent": null, "profile_use_background_image": true, "profile_text_color": "333333", "default_profile_image": false, "id": 2806057411, "profile_background_image_url_https": "https://abs.twimg.com/images/themes/theme1/bg.png", "verified": false, "profile_location": null, "profile_image_url_https": "https://pbs.twimg.com/profile_images/510504354604797952/2_7jrZfy_normal.jpeg", "profile_sidebar_fill_color": "DDEEF6", "entities": {"url": {"urls": [{"url": "http://t.co/J5KT74SEX6", "indices": [0, 22], "expanded_url": "http://talesandtours.com", "display_url": "talesandtours.com"}]}, "description": {"urls": []}}, "followers_count": 40, "profile_sidebar_border_color": "C0DEED", "id_str": "2806057411", "profile_background_color": "C0DEED", "listed_count": 0, "is_translation_enabled": false, "utc_offset": null, "statuses_count": 1083, "description": "Sharing tips on self guided travel & multimedia / audio guides & tours where ever you go! A subsidary of @TalesAndTours. Find us in an appstore near you!", "friends_count": 23, "location": "worldwide", "profile_link_color": "0084B4", "profile_image_url": "http://pbs.twimg.com/profile_images/510504354604797952/2_7jrZfy_normal.jpeg", "following": null, "geo_enabled": true, "profile_banner_url": "https://pbs.twimg.com/profile_banners/2806057411/1410548814", "profile_background_image_url": "http://abs.twimg.com/images/themes/theme1/bg.png", "name": "Tales & Tours Tips \u2708", "lang": "en", "profile_background_tile": false, "favourites_count": 62, "screen_name": "TalesToursTips", "notifications": null, "url": "http://t.co/J5KT74SEX6", "created_at": "Fri Sep 12 18:54:30 +0000 2014", "contributors_enabled": false, "time_zone": null, "protected": false, "default_profile": true, "is_translator": false}, "geo": {"type": "Point", "coordinates": [40.7127837, -74.0059413]}, "in_reply_to_user_id_str": "303491099", "possibly_sensitive": false, "lang": "en", "created_at": "Sat Nov 22 10:38:16 +0000 2014", "in_reply_to_status_id_str": "536106026194706432", "place": {"country_code": "US", "url": "https://api.twitter.com/1.1/geo/id/01a9a39529b27f36.json", "country": "United States", "place_type": "city", "bounding_box": {"type": "Polygon", "coordinates": [[[-74.026675, 40.683935], [-73.910408, 40.683935], [-73.910408, 40.877483], [-74.026675, 40.877483]]]}, "contained_within": [], "full_name": "Manhattan, NY", "attributes": {}, "id": "01a9a39529b27f36", "name": "Manhattan"}, "metadata": {"iso_language_code": "en", "result_type": "recent"}}, "data_point": "none", "user_location": "worldwide", "lon": 40.7127837, "content": "@alicegilder @gh0stparties New York is just fascinating, currently clear. This are some guides to check out: http://t.co/rzlYeqKE95", "tweet_id": 536106380709871616, "user": 2806057411, "time": "Sat Nov 22 10:38:16 +0000 2014", "lat": -74.0059413}, "536107488983416832": {"raw_source": {"contributors": null, "truncated": false, "text": "\u201c@DailyWWENews: Team Authority's Painful Message - SmackDown Fallout - ... - http://t.co/G5FXWtKlGV #wwe #tna http://t.co/kHSfckATOy\u201d", "in_reply_to_status_id": 536024037202219011, "id": 536107488983416832, "favorite_count": 0, "source": "<a href=\"http://twitter.com/download/iphone\" rel=\"nofollow\">Twitter for iPhone</a>", "retweeted": false, "coordinates": {"type": "Point", "coordinates": [-73.91214091, 40.76409426]}, "entities": {"symbols": [], "user_mentions": [{"id": 1056760669, "indices": [1, 14], "id_str": "1056760669", "screen_name": "DailyWWENews", "name": "Daily Wrestling News"}], "hashtags": [{"indices": [100, 104], "text": "wwe"}, {"indices": [105, 109], "text": "tna"}], "urls": [{"url": "http://t.co/G5FXWtKlGV", "indices": [77, 99], "expanded_url": "http://dailywrestlingnews.com/team-authoritys-painful-message-smackdown-fallout-nov-21-2014/", "display_url": "dailywrestlingnews.com/team-authority\u2026"}], "media": [{"source_status_id_str": "536024037202219011", "expanded_url": "http://twitter.com/DailyWWENews/status/536024037202219011/photo/1", "display_url": "pic.twitter.com/kHSfckATOy", "url": "http://t.co/kHSfckATOy", "media_url_https": "https://pbs.twimg.com/media/B3BXBZVCQAAMPKU.jpg", "source_status_id": 536024037202219011, "id_str": "536024037147688960", "sizes": {"small": {"h": 255, "resize": "fit", "w": 340}, "large": {"h": 360, "resize": "fit", "w": 480}, "medium": {"h": 360, "resize": "fit", "w": 480}, "thumb": {"h": 150, "resize": "crop", "w": 150}}, "indices": [110, 132], "type": "photo", "id": 536024037147688960, "media_url": "http://pbs.twimg.com/media/B3BXBZVCQAAMPKU.jpg"}]}, "in_reply_to_screen_name": "DailyWWENews", "in_reply_to_user_id": 1056760669, "retweet_count": 0, "id_str": "536107488983416832", "favorited": false, "user": {"follow_request_sent": null, "profile_use_background_image": true, "profile_text_color": "666666", "default_profile_image": false, "id": 241802289, "profile_background_image_url_https": "https://abs.twimg.com/images/themes/theme9/bg.gif", "verified": false, "profile_location": null, "profile_image_url_https": "https://pbs.twimg.com/profile_images/526425433156620289/5fL-ZFvI_normal.jpeg", "profile_sidebar_fill_color": "252429", "entities": {"description": {"urls": []}}, "followers_count": 172, "profile_sidebar_border_color": "181A1E", "id_str": "241802289", "profile_background_color": "1A1B1F", "listed_count": 2, "is_translation_enabled": false, "utc_offset": -21600, "statuses_count": 9571, "description": "Life long wrestling fan.", "friends_count": 162, "location": "Parts Unknown", "profile_link_color": "2FC2EF", "profile_image_url": "http://pbs.twimg.com/profile_images/526425433156620289/5fL-ZFvI_normal.jpeg", "following": null, "geo_enabled": true, "profile_banner_url": "https://pbs.twimg.com/profile_banners/241802289/1416004672", "profile_background_image_url": "http://abs.twimg.com/images/themes/theme9/bg.gif", "name": "Dead Man", "lang": "en", "profile_background_tile": false, "favourites_count": 17044, "screen_name": "DarksiderNYC", "notifications": null, "url": null, "created_at": "Sun Jan 23 05:07:48 +0000 2011", "contributors_enabled": false, "time_zone": "Central Time (US & Canada)", "protected": false, "default_profile": false, "is_translator": false}, "geo": {"type": "Point", "coordinates": [40.76409426, -73.91214091]}, "in_reply_to_user_id_str": "1056760669", "possibly_sensitive": false, "lang": "en", "created_at": "Sat Nov 22 10:42:40 +0000 2014", "in_reply_to_status_id_str": "536024037202219011", "place": {"country_code": "US", "url": "https://api.twitter.com/1.1/geo/id/00c39537733fa112.json", "country": "United States", "place_type": "city", "bounding_box": {"type": "Polygon", "coordinates": [[[-73.962582, 40.541722], [-73.699793, 40.541722], [-73.699793, 40.8000371], [-73.962582, 40.8000371]]]}, "contained_within": [], "full_name": "Queens, NY", "attributes": {}, "id": "00c39537733fa112", "name": "Queens"}, "metadata": {"iso_language_code": "en", "result_type": "recent"}}, "data_point": "none", "user_location": "Parts Unknown", "lon": 40.76409426, "content": "\u201c@DailyWWENews: Team Authority's Painful Message - SmackDown Fallout - ... - http://t.co/G5FXWtKlGV #wwe #tna http://t.co/kHSfckATOy\u201d", "tweet_id": 536107488983416832, "user": 241802289, "time": "Sat Nov 22 10:42:40 +0000 2014", "lat": -73.91214091}, "536106688055873536": {"raw_source": {"contributors": null, "truncated": false, "text": "All up in the BK. Been at work since 3:30am. Caffeinated. Health expo. I am only capable of sentence fragments.", "in_reply_to_status_id": null, "id": 536106688055873536, "favorite_count": 0, "source": "<a href=\"http://twitter.com/download/iphone\" rel=\"nofollow\">Twitter for iPhone</a>", "retweeted": false, "coordinates": {"type": "Point", "coordinates": [-73.97790437, 40.68583249]}, "entities": {"symbols": [], "user_mentions": [], "hashtags": [], "urls": []}, "in_reply_to_screen_name": null, "in_reply_to_user_id": null, "retweet_count": 0, "id_str": "536106688055873536", "favorited": false, "user": {"follow_request_sent": null, "profile_use_background_image": true, "profile_text_color": "333333", "default_profile_image": false, "id": 130654973, "profile_background_image_url_https": "https://pbs.twimg.com/profile_background_images/317958869/outerspace.jpg", "verified": false, "profile_location": null, "profile_image_url_https": "https://pbs.twimg.com/profile_images/521737993695268864/nry0pTMv_normal.jpeg", "profile_sidebar_fill_color": "EFEFEF", "entities": {"url": {"urls": [{"url": "http://t.co/FV3sfELtPo", "indices": [0, 22], "expanded_url": "http://inourgloryofficial.bandcamp.com", "display_url": "inourgloryofficial.bandcamp.com"}]}, "description": {"urls": []}}, "followers_count": 428, "profile_sidebar_border_color": "EEEEEE", "id_str": "130654973", "profile_background_color": "131516", "listed_count": 0, "is_translation_enabled": false, "utc_offset": -18000, "statuses_count": 8452, "description": "@InOurGlory", "friends_count": 164, "location": "NJ | NYC", "profile_link_color": "009999", "profile_image_url": "http://pbs.twimg.com/profile_images/521737993695268864/nry0pTMv_normal.jpeg", "following": null, "geo_enabled": true, "profile_banner_url": "https://pbs.twimg.com/profile_banners/130654973/1415161731", "profile_background_image_url": "http://pbs.twimg.com/profile_background_images/317958869/outerspace.jpg", "name": "Gina Petro", "lang": "en", "profile_background_tile": true, "favourites_count": 1817, "screen_name": "GinaIOG", "notifications": null, "url": "http://t.co/FV3sfELtPo", "created_at": "Wed Apr 07 22:57:08 +0000 2010", "contributors_enabled": false, "time_zone": "Quito", "protected": false, "default_profile": false, "is_translator": false}, "geo": {"type": "Point", "coordinates": [40.68583249, -73.97790437]}, "in_reply_to_user_id_str": null, "lang": "en", "created_at": "Sat Nov 22 10:39:29 +0000 2014", "in_reply_to_status_id_str": null, "place": {"country_code": "US", "url": "https://api.twitter.com/1.1/geo/id/011add077f4d2da3.json", "country": "United States", "place_type": "city", "bounding_box": {"type": "Polygon", "coordinates": [[[-74.041878, 40.570842], [-73.855673, 40.570842], [-73.855673, 40.739434], [-74.041878, 40.739434]]]}, "contained_within": [], "full_name": "Brooklyn, NY", "attributes": {}, "id": "011add077f4d2da3", "name": "Brooklyn"}, "metadata": {"iso_language_code": "en", "result_type": "recent"}}, "data_point": "none", "user_location": "NJ | NYC", "lon": 40.68583249, "content": "All up in the BK. Been at work since 3:30am. Caffeinated. Health expo. I am only capable of sentence fragments.", "tweet_id": 536106688055873536, "user": 130654973, "time": "Sat Nov 22 10:39:29 +0000 2014", "lat": -73.97790437}, "536107106647015424": {"raw_source": {"contributors": null, "truncated": false, "text": "syg kalau aku balikan sm mantan, kamu gimana ? | gpp kok | yakin ? | gpp NYET!! Nyante aja kali NJING! | -_-", "in_reply_to_status_id": null, "id": 536107106647015424, "favorite_count": 0, "source": "<a href=\"http://twitter.com\" rel=\"nofollow\">Twitter Web Client</a>", "retweeted": false, "coordinates": {"type": "Point", "coordinates": [0.0, 0.0]}, "entities": {"symbols": [], "user_mentions": [], "hashtags": [], "urls": []}, "in_reply_to_screen_name": null, "in_reply_to_user_id": null, "retweet_count": 0, "id_str": "536107106647015424", "favorited": false, "user": {"follow_request_sent": null, "profile_use_background_image": true, "profile_text_color": "3D1957", "default_profile_image": false, "id": 2603626446, "profile_background_image_url_https": "https://abs.twimg.com/images/themes/theme10/bg.gif", "verified": false, "profile_location": null, "profile_image_url_https": "https://pbs.twimg.com/profile_images/512131230125391872/HrVhqOS8_normal.jpeg", "profile_sidebar_fill_color": "7AC3EE", "entities": {"description": {"urls": []}}, "followers_count": 192, "profile_sidebar_border_color": "65B0DA", "id_str": "2603626446", "profile_background_color": "642D8B", "listed_count": 0, "is_translation_enabled": false, "utc_offset": null, "statuses_count": 4412, "description": "get your love | follback just mention", "friends_count": 574, "location": "new york", "profile_link_color": "FF0000", "profile_image_url": "http://pbs.twimg.com/profile_images/512131230125391872/HrVhqOS8_normal.jpeg", "following": null, "geo_enabled": true, "profile_banner_url": "https://pbs.twimg.com/profile_banners/2603626446/1416323362", "profile_background_image_url": "http://abs.twimg.com/images/themes/theme10/bg.gif", "name": "Ritma aulia", "lang": "id", "profile_background_tile": true, "favourites_count": 25, "screen_name": "RitmaAulia", "notifications": null, "url": null, "created_at": "Fri Jul 04 15:09:04 +0000 2014", "contributors_enabled": false, "time_zone": null, "protected": false, "default_profile": false, "is_translator": false}, "geo": {"type": "Point", "coordinates": [0.0, 0.0]}, "in_reply_to_user_id_str": null, "lang": "in", "created_at": "Sat Nov 22 10:41:09 +0000 2014", "in_reply_to_status_id_str": null, "place": {"country_code": "ID", "url": "https://api.twitter.com/1.1/geo/id/93aa30b3e9be6b59.json", "country": "Indonesia", "place_type": "city", "bounding_box": {"type": "Polygon", "coordinates": [[[106.704469, -6.189221], [106.783525, -6.189221], [106.783525, -6.112283], [106.704469, -6.112283]]]}, "contained_within": [], "full_name": "Cengkareng, Jakarta Barat", "attributes": {}, "id": "93aa30b3e9be6b59", "name": "Cengkareng"}, "metadata": {"iso_language_code": "in", "result_type": "recent"}}, "data_point": "none", "user_location": "new york", "lon": 0.0, "content": "syg kalau aku balikan sm mantan, kamu gimana ? | gpp kok | yakin ? | gpp NYET!! Nyante aja kali NJING! | -_-", "tweet_id": 536107106647015424, "user": 2603626446, "time": "Sat Nov 22 10:41:09 +0000 2014", "lat": 0.0}, "536107739148460032": {"raw_source": {"contributors": null, "truncated": false, "text": "\u201c@NYCTSubway: #SubwayNews Water from broken main pours into subway tunnel at E.143rd St #6 station http://t.co/l37b5TqlRB\u201d", "in_reply_to_status_id": 536028447873576960, "id": 536107739148460032, "favorite_count": 0, "source": "<a href=\"http://twitter.com/download/iphone\" rel=\"nofollow\">Twitter for iPhone</a>", "retweeted": false, "coordinates": {"type": "Point", "coordinates": [-73.91219131, 40.76406651]}, "entities": {"symbols": [], "user_mentions": [{"id": 66379182, "indices": [1, 12], "id_str": "66379182", "screen_name": "NYCTSubway", "name": "NYCT Subway Service"}], "hashtags": [{"indices": [14, 25], "text": "SubwayNews"}], "urls": [], "media": [{"source_status_id_str": "536028447873576960", "expanded_url": "http://twitter.com/NYCTSubway/status/536028447873576960/photo/1", "display_url": "pic.twitter.com/l37b5TqlRB", "url": "http://t.co/l37b5TqlRB", "media_url_https": "https://pbs.twimg.com/media/B3BbBzoCQAAByD3.jpg", "source_status_id": 536028447873576960, "id_str": "536028442253213696", "sizes": {"small": {"h": 453, "resize": "fit", "w": 340}, "large": {"h": 1024, "resize": "fit", "w": 768}, "medium": {"h": 800, "resize": "fit", "w": 600}, "thumb": {"h": 150, "resize": "crop", "w": 150}}, "indices": [99, 121], "type": "photo", "id": 536028442253213696, "media_url": "http://pbs.twimg.com/media/B3BbBzoCQAAByD3.jpg"}]}, "in_reply_to_screen_name": "NYCTSubway", "in_reply_to_user_id": 66379182, "retweet_count": 0, "id_str": "536107739148460032", "favorited": false, "user": {"follow_request_sent": null, "profile_use_background_image": true, "profile_text_color": "666666", "default_profile_image": false, "id": 241802289, "profile_background_image_url_https": "https://abs.twimg.com/images/themes/theme9/bg.gif", "verified": false, "profile_location": null, "profile_image_url_https": "https://pbs.twimg.com/profile_images/526425433156620289/5fL-ZFvI_normal.jpeg", "profile_sidebar_fill_color": "252429", "entities": {"description": {"urls": []}}, "followers_count": 172, "profile_sidebar_border_color": "181A1E", "id_str": "241802289", "profile_background_color": "1A1B1F", "listed_count": 2, "is_translation_enabled": false, "utc_offset": -21600, "statuses_count": 9573, "description": "Life long wrestling fan.", "friends_count": 162, "location": "Parts Unknown", "profile_link_color": "2FC2EF", "profile_image_url": "http://pbs.twimg.com/profile_images/526425433156620289/5fL-ZFvI_normal.jpeg", "following": null, "geo_enabled": true, "profile_banner_url": "https://pbs.twimg.com/profile_banners/241802289/1416004672", "profile_background_image_url": "http://abs.twimg.com/images/themes/theme9/bg.gif", "name": "Dead Man", "lang": "en", "profile_background_tile": false, "favourites_count": 17046, "screen_name": "DarksiderNYC", "notifications": null, "url": null, "created_at": "Sun Jan 23 05:07:48 +0000 2011", "contributors_enabled": false, "time_zone": "Central Time (US & Canada)", "protected": false, "default_profile": false, "is_translator": false}, "geo": {"type": "Point", "coordinates": [40.76406651, -73.91219131]}, "in_reply_to_user_id_str": "66379182", "possibly_sensitive": false, "lang": "en", "created_at": "Sat Nov 22 10:43:40 +0000 2014", "in_reply_to_status_id_str": "536028447873576960", "place": {"country_code": "US", "url": "https://api.twitter.com/1.1/geo/id/00c39537733fa112.json", "country": "United States", "place_type": "city", "bounding_box": {"type": "Polygon", "coordinates": [[[-73.962582, 40.541722], [-73.699793, 40.541722], [-73.699793, 40.8000371], [-73.962582, 40.8000371]]]}, "contained_within": [], "full_name": "Queens, NY", "attributes": {}, "id": "00c39537733fa112", "name": "Queens"}, "metadata": {"iso_language_code": "en", "result_type": "recent"}}, "data_point": "none", "user_location": "Parts Unknown", "lon": 40.76406651, "content": "\u201c@NYCTSubway: #SubwayNews Water from broken main pours into subway tunnel at E.143rd St #6 station http://t.co/l37b5TqlRB\u201d", "tweet_id": 536107739148460032, "user": 241802289, "time": "Sat Nov 22 10:43:40 +0000 2014", "lat": -73.91219131}, "536107343831130112": {"raw_source": {"contributors": null, "truncated": false, "text": "Que disfruten de este bello d\u00eda. http://t.co/7DWWw7xCFF", "in_reply_to_status_id": null, "id": 536107343831130112, "favorite_count": 0, "source": "<a href=\"http://twitter.com/download/iphone\" rel=\"nofollow\">Twitter for iPhone</a>", "retweeted": false, "coordinates": {"type": "Point", "coordinates": [-73.85657841, 40.7463398]}, "entities": {"symbols": [], "user_mentions": [], "hashtags": [], "urls": [], "media": [{"expanded_url": "http://twitter.com/JairoCoronado18/status/536107343831130112/photo/1", "display_url": "pic.twitter.com/7DWWw7xCFF", "url": "http://t.co/7DWWw7xCFF", "media_url_https": "https://pbs.twimg.com/media/B3Ciw34IIAEiGbk.jpg", "id_str": "536107316173873153", "sizes": {"large": {"h": 1024, "resize": "fit", "w": 577}, "small": {"h": 603, "resize": "fit", "w": 340}, "medium": {"h": 1024, "resize": "fit", "w": 577}, "thumb": {"h": 150, "resize": "crop", "w": 150}}, "indices": [33, 55], "type": "photo", "id": 536107316173873153, "media_url": "http://pbs.twimg.com/media/B3Ciw34IIAEiGbk.jpg"}]}, "in_reply_to_screen_name": null, "in_reply_to_user_id": null, "retweet_count": 0, "id_str": "536107343831130112", "favorited": false, "user": {"follow_request_sent": null, "profile_use_background_image": true, "profile_text_color": "333333", "default_profile_image": false, "id": 332566163, "profile_background_image_url_https": "https://abs.twimg.com/images/themes/theme1/bg.png", "verified": false, "profile_location": null, "profile_image_url_https": "https://pbs.twimg.com/profile_images/378800000415934763/5d15a4ff3f12e155936fe13e29235ea5_normal.jpeg", "profile_sidebar_fill_color": "DDEEF6", "entities": {"description": {"urls": []}}, "followers_count": 10, "profile_sidebar_border_color": "C0DEED", "id_str": "332566163", "profile_background_color": "C0DEED", "listed_count": 0, "is_translation_enabled": false, "utc_offset": null, "statuses_count": 459, "description": "Soy una persona que le gusta practicar deportes, salir a dibertirce sanamente y hacer buenos amigos.", "friends_count": 63, "location": "Nueva York E,E,U,U,", "profile_link_color": "0084B4", "profile_image_url": "http://pbs.twimg.com/profile_images/378800000415934763/5d15a4ff3f12e155936fe13e29235ea5_normal.jpeg", "following": null, "geo_enabled": true, "profile_background_image_url": "http://abs.twimg.com/images/themes/theme1/bg.png", "name": "Jairo Coronado", "lang": "es", "profile_background_tile": false, "favourites_count": 6, "screen_name": "JairoCoronado18", "notifications": null, "url": null, "created_at": "Sun Jul 10 01:45:06 +0000 2011", "contributors_enabled": false, "time_zone": null, "protected": false, "default_profile": true, "is_translator": false}, "geo": {"type": "Point", "coordinates": [40.7463398, -73.85657841]}, "in_reply_to_user_id_str": null, "possibly_sensitive": false, "lang": "es", "created_at": "Sat Nov 22 10:42:05 +0000 2014", "in_reply_to_status_id_str": null, "place": {"country_code": "US", "url": "https://api.twitter.com/1.1/geo/id/00c39537733fa112.json", "country": "United States", "place_type": "city", "bounding_box": {"type": "Polygon", "coordinates": [[[-73.962582, 40.541722], [-73.699793, 40.541722], [-73.699793, 40.8000371], [-73.962582, 40.8000371]]]}, "contained_within": [], "full_name": "Queens, NY", "attributes": {}, "id": "00c39537733fa112", "name": "Queens"}, "metadata": {"iso_language_code": "es", "result_type": "recent"}}, "data_point": "none", "user_location": "Nueva York E,E,U,U,", "lon": 40.7463398, "content": "Que disfruten de este bello d\u00eda. http://t.co/7DWWw7xCFF", "tweet_id": 536107343831130112, "user": 332566163, "time": "Sat Nov 22 10:42:05 +0000 2014", "lat": -73.85657841}, "536107418842062848": {"raw_source": {"contributors": null, "truncated": false, "text": "Slumpedddd", "in_reply_to_status_id": null, "id": 536107418842062848, "favorite_count": 0, "source": "<a href=\"http://twitter.com/download/iphone\" rel=\"nofollow\">Twitter for iPhone</a>", "retweeted": false, "coordinates": {"type": "Point", "coordinates": [-73.84478106, 40.73750367]}, "entities": {"symbols": [], "user_mentions": [], "hashtags": [], "urls": []}, "in_reply_to_screen_name": null, "in_reply_to_user_id": null, "retweet_count": 0, "id_str": "536107418842062848", "favorited": false, "user": {"follow_request_sent": null, "profile_use_background_image": true, "profile_text_color": "333333", "default_profile_image": false, "id": 704185214, "profile_background_image_url_https": "https://abs.twimg.com/images/themes/theme1/bg.png", "verified": false, "profile_location": null, "profile_image_url_https": "https://pbs.twimg.com/profile_images/535065688306888705/mZi4J0h1_normal.jpeg", "profile_sidebar_fill_color": "DDEEF6", "entities": {"description": {"urls": []}}, "followers_count": 418, "profile_sidebar_border_color": "C0DEED", "id_str": "704185214", "profile_background_color": "C0DEED", "listed_count": 0, "is_translation_enabled": false, "utc_offset": null, "statuses_count": 20767, "description": "IG: Slowbuckss", "friends_count": 431, "location": "Queens Ny", "profile_link_color": "B30000", "profile_image_url": "http://pbs.twimg.com/profile_images/535065688306888705/mZi4J0h1_normal.jpeg", "following": null, "geo_enabled": true, "profile_banner_url": "https://pbs.twimg.com/profile_banners/704185214/1414509237", "profile_background_image_url": "http://abs.twimg.com/images/themes/theme1/bg.png", "name": "SupremeDopeDealer", "lang": "en", "profile_background_tile": false, "favourites_count": 1019, "screen_name": "Based_GioTk", "notifications": null, "url": null, "created_at": "Thu Jul 19 02:16:47 +0000 2012", "contributors_enabled": false, "time_zone": null, "protected": false, "default_profile": false, "is_translator": false}, "geo": {"type": "Point", "coordinates": [40.73750367, -73.84478106]}, "in_reply_to_user_id_str": null, "lang": "en", "created_at": "Sat Nov 22 10:42:23 +0000 2014", "in_reply_to_status_id_str": null, "place": {"country_code": "US", "url": "https://api.twitter.com/1.1/geo/id/00c39537733fa112.json", "country": "United States", "place_type": "city", "bounding_box": {"type": "Polygon", "coordinates": [[[-73.962582, 40.541722], [-73.699793, 40.541722], [-73.699793, 40.8000371], [-73.962582, 40.8000371]]]}, "contained_within": [], "full_name": "Queens, NY", "attributes": {}, "id": "00c39537733fa112", "name": "Queens"}, "metadata": {"iso_language_code": "en", "result_type": "recent"}}, "data_point": "none", "user_location": "Queens Ny", "lon": 40.73750367, "content": "Slumpedddd", "tweet_id": 536107418842062848, "user": 704185214, "time": "Sat Nov 22 10:42:23 +0000 2014", "lat": -73.84478106}, "536107422348488705": {"raw_source": {"contributors": null, "truncated": false, "text": "This is at the train station in the BX. 143 Street/ST MARY'S STREET http://t.co/VwlFM4DCsU", "in_reply_to_status_id": null, "id": 536107422348488705, "favorite_count": 0, "source": "<a href=\"http://twitter.com/download/android\" rel=\"nofollow\">Twitter for Android</a>", "retweeted": false, "coordinates": {"type": "Point", "coordinates": [-73.9924415, 40.7368402]}, "entities": {"symbols": [], "user_mentions": [], "hashtags": [], "urls": [], "media": [{"expanded_url": "http://twitter.com/HERSEYSDARK/status/536107422348488705/photo/1", "display_url": "pic.twitter.com/VwlFM4DCsU", "url": "http://t.co/VwlFM4DCsU", "media_url_https": "https://pbs.twimg.com/media/B3Ci2qoCAAA-T2W.jpg", "id_str": "536107415695917056", "sizes": {"small": {"h": 453, "resize": "fit", "w": 340}, "large": {"h": 960, "resize": "fit", "w": 720}, "medium": {"h": 800, "resize": "fit", "w": 600}, "thumb": {"h": 150, "resize": "crop", "w": 150}}, "indices": [68, 90], "type": "photo", "id": 536107415695917056, "media_url": "http://pbs.twimg.com/media/B3Ci2qoCAAA-T2W.jpg"}]}, "in_reply_to_screen_name": null, "in_reply_to_user_id": null, "retweet_count": 0, "id_str": "536107422348488705", "favorited": false, "user": {"follow_request_sent": null, "profile_use_background_image": true, "profile_text_color": "333333", "default_profile_image": false, "id": 160234973, "profile_background_image_url_https": "https://abs.twimg.com/images/themes/theme1/bg.png", "verified": false, "profile_location": null, "profile_image_url_https": "https://pbs.twimg.com/profile_images/516138165980397569/UuBM484v_normal.jpeg", "profile_sidebar_fill_color": "DDEEF6", "entities": {"description": {"urls": []}}, "followers_count": 88, "profile_sidebar_border_color": "C0DEED", "id_str": "160234973", "profile_background_color": "C0DEED", "listed_count": 1, "is_translation_enabled": false, "utc_offset": -18000, "statuses_count": 19177, "description": "TALL,DARK & HANDSOME\r\nLOVED BY MANY,HATED BY FEW,& RESPECTED BY ALL!", "friends_count": 98, "location": "SHOALIN aka STATEN ISLAND", "profile_link_color": "0084B4", "profile_image_url": "http://pbs.twimg.com/profile_images/516138165980397569/UuBM484v_normal.jpeg", "following": null, "geo_enabled": true, "profile_banner_url": "https://pbs.twimg.com/profile_banners/160234973/1357631139", "profile_background_image_url": "http://abs.twimg.com/images/themes/theme1/bg.png", "name": "KARL D.GREEN", "lang": "en", "profile_background_tile": false, "favourites_count": 17384, "screen_name": "HERSEYSDARK", "notifications": null, "url": null, "created_at": "Sun Jun 27 15:54:31 +0000 2010", "contributors_enabled": false, "time_zone": "Eastern Time (US & Canada)", "protected": false, "default_profile": true, "is_translator": false}, "geo": {"type": "Point", "coordinates": [40.7368402, -73.9924415]}, "in_reply_to_user_id_str": null, "possibly_sensitive": false, "lang": "en", "created_at": "Sat Nov 22 10:42:24 +0000 2014", "in_reply_to_status_id_str": null, "place": {"country_code": "US", "url": "https://api.twitter.com/1.1/geo/id/01a9a39529b27f36.json", "country": "United States", "place_type": "city", "bounding_box": {"type": "Polygon", "coordinates": [[[-74.026675, 40.683935], [-73.910408, 40.683935], [-73.910408, 40.877483], [-74.026675, 40.877483]]]}, "contained_within": [], "full_name": "Manhattan, NY", "attributes": {}, "id": "01a9a39529b27f36", "name": "Manhattan"}, "metadata": {"iso_language_code": "en", "result_type": "recent"}}, "data_point": "none", "user_location": "SHOALIN aka STATEN ISLAND", "lon": 40.7368402, "content": "This is at the train station in the BX. 143 Street/ST MARY'S STREET http://t.co/VwlFM4DCsU", "tweet_id": 536107422348488705, "user": 160234973, "time": "Sat Nov 22 10:42:24 +0000 2014", "lat": -73.9924415}, "536107430045044736": {"raw_source": {"contributors": null, "truncated": false, "text": "Got that pic with @Dyro \ud83d\ude0d http://t.co/ET9BPdbU4c", "in_reply_to_status_id": null, "id": 536107430045044736, "favorite_count": 0, "source": "<a href=\"http://twitter.com/download/iphone\" rel=\"nofollow\">Twitter for iPhone</a>", "retweeted": false, "coordinates": {"type": "Point", "coordinates": [-73.79702769, 40.71937605]}, "entities": {"symbols": [], "user_mentions": [{"id": 125077669, "indices": [18, 23], "id_str": "125077669", "screen_name": "Dyro", "name": "Dyro"}], "hashtags": [], "urls": [], "media": [{"expanded_url": "http://twitter.com/nhidiep23/status/536107430045044736/photo/1", "display_url": "pic.twitter.com/ET9BPdbU4c", "url": "http://t.co/ET9BPdbU4c", "media_url_https": "https://pbs.twimg.com/media/B3Ci3IoIgAEEskn.jpg", "id_str": "536107423749406721", "sizes": {"small": {"h": 453, "resize": "fit", "w": 340}, "large": {"h": 1024, "resize": "fit", "w": 768}, "medium": {"h": 800, "resize": "fit", "w": 600}, "thumb": {"h": 150, "resize": "crop", "w": 150}}, "indices": [26, 48], "type": "photo", "id": 536107423749406721, "media_url": "http://pbs.twimg.com/media/B3Ci3IoIgAEEskn.jpg"}]}, "in_reply_to_screen_name": null, "in_reply_to_user_id": null, "retweet_count": 0, "id_str": "536107430045044736", "favorited": false, "user": {"follow_request_sent": null, "profile_use_background_image": true, "profile_text_color": "333333", "default_profile_image": false, "id": 628892102, "profile_background_image_url_https": "https://abs.twimg.com/images/themes/theme1/bg.png", "verified": false, "profile_location": null, "profile_image_url_https": "https://pbs.twimg.com/profile_images/529009494953844736/gN4RzdQ2_normal.jpeg", "profile_sidebar_fill_color": "DDEEF6", "entities": {"description": {"urls": []}}, "followers_count": 343, "profile_sidebar_border_color": "C0DEED", "id_str": "628892102", "profile_background_color": "C0DEED", "listed_count": 1, "is_translation_enabled": false, "utc_offset": null, "statuses_count": 8935, "description": "St. John's University", "friends_count": 131, "location": "GA/NYC", "profile_link_color": "0084B4", "profile_image_url": "http://pbs.twimg.com/profile_images/529009494953844736/gN4RzdQ2_normal.jpeg", "following": null, "geo_enabled": true, "profile_banner_url": "https://pbs.twimg.com/profile_banners/628892102/1409200001", "profile_background_image_url": "http://abs.twimg.com/images/themes/theme1/bg.png", "name": "nhi diep", "lang": "en", "profile_background_tile": false, "favourites_count": 13062, "screen_name": "nhidiep23", "notifications": null, "url": null, "created_at": "Sat Jul 07 01:42:14 +0000 2012", "contributors_enabled": false, "time_zone": null, "protected": false, "default_profile": true, "is_translator": false}, "geo": {"type": "Point", "coordinates": [40.71937605, -73.79702769]}, "in_reply_to_user_id_str": null, "possibly_sensitive": false, "lang": "en", "created_at": "Sat Nov 22 10:42:26 +0000 2014", "in_reply_to_status_id_str": null, "place": {"country_code": "US", "url": "https://api.twitter.com/1.1/geo/id/00c39537733fa112.json", "country": "United States", "place_type": "city", "bounding_box": {"type": "Polygon", "coordinates": [[[-73.962582, 40.541722], [-73.699793, 40.541722], [-73.699793, 40.8000371], [-73.962582, 40.8000371]]]}, "contained_within": [], "full_name": "Queens, NY", "attributes": {}, "id": "00c39537733fa112", "name": "Queens"}, "metadata": {"iso_language_code": "en", "result_type": "recent"}}, "data_point": "none", "user_location": "GA/NYC", "lon": 40.71937605, "content": "Got that pic with @Dyro \ud83d\ude0d http://t.co/ET9BPdbU4c", "tweet_id": 536107430045044736, "user": 628892102, "time": "Sat Nov 22 10:42:26 +0000 2014", "lat": -73.79702769}}